Workbook

Sheet Screening
A1: # | B1: Year | C1: Title | D1: Found in search(es) | E1: Duplicate across searches? | F1: Decision | G1: Priority | H1: Relevance category | I1: AI / ML / QML? | J1: What is predicted? | K1: Task | L1: Dataset / N | M1: Input / representation | N1: Models / approach | O1: Validation | P1: Reported result | Q1: Quantum relation | R1: Why useful for our paper? | S1: Source title | T1: DOI | U1: Scopus link | V1: Open access
A2: 1 | B2: 2018 | C2: QSAR modeling in ecotoxicological risk assessment: application to the prediction of acute contact toxicity of pesticides on bees (Apis mellifera L.) | D2: Bee toxicity ML | E2: No | F2: Core | G2: High | H2: Direct honey-bee toxicity ML / QSAR | I2: ML / QSAR | J2: Honey-bee / Apis mellifera toxicity | K2: Classification / regression | L2: 111 pesticides | M2: NR in supplied metadata | N2: ML / QSAR model | O2: External validation | P2: A good correlation between predicted and experimental values was found (R2 = 0.97 and RMSE = 0.14). | Q2: No | R2: Direct prior art for the target endpoint; useful for comparing datasets, molecular representations, classical baselines, validation and reported limitations. | S2: Environmental Science and Pollution Research | T2: https://doi.org/10.1007/s11356-017-0498-9 | U2: https://www.scopus.com/pages/publications/85032016580?origin=resultslist
A3: 2 | B3: 2026 | C3: Meditox: integrating machine learning and molecular data for accurate drug toxicity prediction | D3: Bee toxicity ML | Molecular toxicity ML | E3: Yes | F3: Core | G3: High | H3: Transferable classical molecular toxicity / ecotoxicity ML | I3: DL / neural network | J3: Mutagenicity / Ames | K3: Predictive modeling / methodology | L3: NR in supplied metadata | M3: Molecular fingerprints; Molecular descriptors | N3: ML / QSAR model | O3: External test; Cross-validation | P3: High accuracy and generalizability were validated by external testing and cross-validation. | Q3: No | R3: Transferable methodology for strengthening classical baselines, representation analysis, validation, interpretability or generalization beyond the base bee-toxicity study. | S3: Recent Trends in Data Analytics and Computing: Exploring Emerging Technologies and Future Directions, A proceeding of ICADAC – 2025 | T3: https://doi.org/10.1201/9781003724995-17 | U3: https://www.scopus.com/pages/publications/105027494742?origin=resultslist
A4: 3 | B4: 2023 | C4: Application of machine learning models to predict cytotoxicity of ionic liquids using VolSurf principal properties | D4: Bee toxicity ML | E4: No | F4: Exclude | G4: Low | H4: Search noise / outside scope | I4: ML / QSAR | J4: Cytotoxicity | K4: Regression | L4: NR in supplied metadata | M4: Molecular descriptors | N4: Random Forest; XGBoost; Gradient Boosting; SVM/SVR | O4: NR in supplied metadata | P4: Analysis of the performance of the models on predicting the out-of-sample data set showed that the Extreme Gradient Boosting (XGBoost) supervised machine learning model is the best in predicting with the highest test score (R2 = 0.79). | Q4: No | R4: Outside the bee-toxicity, transferable molecular-toxicity, or molecular-QML scope of the three searches. | S4: Computational Toxicology | T4: https://doi.org/10.1016/j.comtox.2023.100266 | U4: https://www.scopus.com/pages/publications/85150289613?origin=resultslist
A5: 4 | B5: 2016 | C5: Extending standard testing period in honeybees to predict lifespan impacts of pesticides and heavy metals using dynamic energy budget modelling | D5: Bee toxicity ML | E5: No | F5: Supporting | G5: Medium | H5: Honey-bee toxicology / problem context | I5: Non-ML / experimental or contextual | J5: Honey-bee / Apis mellifera toxicity | K5: Regression | L5: NR in supplied metadata | M5: NR in supplied metadata | N5: NR in supplied metadata | O5: NR in supplied metadata | P5: NR in supplied abstract | Q5: No | R5: Useful for problem justification, endpoint interpretation, exposure mechanisms, species sensitivity or limitations not captured by structure-only ML. | S5: Scientific Reports | T5: https://doi.org/10.1038/srep37655 | U5: https://www.scopus.com/pages/publications/85007010733?origin=resultslist | V5: All Open Access; Gold Open Access; Green Open Access
A6: 5 | B6: 2024 | C6: Predictionof Environmental FateandToxicityofInsecticidesUsing Multi-Target QSAR Approach | D6: Bee toxicity ML | E6: No | F6: Exclude | G6: Low | H6: Search noise / outside scope | I6: ML / QSAR | J6: Chemical ecotoxicity | K6: Regression | L6: NR in supplied metadata | M6: Molecular descriptors; PCA / reduced features | N6: Neural network | O6: External validation | P6: The developed well-trained model (RMSE=0.83, MPE=0.004, CCC=0.82, IIC=0.78, R2=0.69) was statistically robust as indicated by the external validation parameters (RMSE=0.93, MPE=0.008, CCC=0.77, IIC=0.68, R2=0.61). | Q6: No | R6: Outside the bee-toxicity, transferable molecular-toxicity, or molecular-QML scope of the three searches. | S6: Chemistry and Biodiversity | T6: https://doi.org/10.1002/cbdv.202301213 | U6: https://www.scopus.com/pages/publications/85179909139?origin=resultslist
A7: 6 | B7: 2023 | C7: Machine learning-driven QSAR models for predicting the mixture toxicity of nanoparticles | D7: Bee toxicity ML | E7: No | F7: Exclude | G7: Low | H7: Search noise / outside scope | I7: ML / QSAR | J7: Cytotoxicity | K7: Classification / regression | L7: NR in supplied metadata | M7: Molecular descriptors | N7: SVM/SVR; Neural network | O7: Applicability-domain analysis | P7: NR in supplied abstract | Q7: No | R7: Outside the bee-toxicity, transferable molecular-toxicity, or molecular-QML scope of the three searches. | S7: Environment International | T7: https://doi.org/10.1016/j.envint.2023.108025 | U7: https://www.scopus.com/pages/publications/85162138083?origin=resultslist | V7: All Open Access; Gold Open Access; Green Open Access
A8: 7 | B8: 2026 | C8: Joint exposure to sulfoxaflor and prochloraz alters enzymatic and genetic profiles in honey bees (Apis mellifera L.) | D8: Bee toxicity ML | E8: No | F8: Supporting | G8: Medium | H8: Honey-bee toxicology / problem context | I8: Non-ML / experimental or contextual | J8: Honey-bee pesticide mixture toxicity | K8: Experimental / risk-assessment study | L8: NR in supplied metadata | M8: NR in supplied metadata | N8: NR in supplied metadata | O8: NR in supplied metadata | P8: NR in supplied abstract | Q8: No | R8: Useful for problem justification, endpoint interpretation, exposure mechanisms, species sensitivity or limitations not captured by structure-only ML. | S8: Pesticide Biochemistry and Physiology | T8: https://doi.org/10.1016/j.pestbp.2026.106953 | U8: https://www.scopus.com/pages/publications/105029319222?origin=resultslist
A9: 8 | B9: 2026 | C9: BeeMSAI: A multi-dimensional evaluation strategy for honeybee toxicity in agrochemicals integrating mode of action, structural analysis, and AI–powered prediction | D9: Bee toxicity ML | E9: No | F9: Core | G9: High | H9: Direct honey-bee toxicity ML / QSAR | I9: ML / QSAR | J9: Honey-bee / Apis mellifera toxicity | K9: Classification | L9: NR in supplied metadata | M9: NR in supplied metadata | N9: SVM/SVR; GAT; Neural network | O9: NR in supplied metadata | P9: The support vector machine model showed robust predictive performance with an overall accuracy of 81.82 %, with the accuracy for neonicotinoids and new pesticides being 84.21 % and 80.77 %, respectively. | Q9: No | R9: Direct prior art for the target endpoint; useful for comparing datasets, molecular representations, classical baselines, validation and reported limitations. | S9: Journal of Hazardous Materials | T9: https://doi.org/10.1016/j.jhazmat.2025.141018 | U9: https://www.scopus.com/pages/publications/105027181923?origin=resultslist
A10: 9 | B10: 2020 | C10: QSAR modeling of the toxicity classification of superparamagnetic iron oxide nanoparticles (SPIONs) in stem-cell monitoring applications: An integrated study from data curation to model development | D10: Bee toxicity ML | E10: No | F10: Exclude | G10: Low | H10: Search noise / outside scope | I10: ML / QSAR | J10: Chemical / molecular toxicity | K10: Classification | L10: NR in supplied metadata | M10: Molecular graphs | N10: ML / QSAR model | O10: NR in supplied metadata | P10: NR in supplied abstract | Q10: No | R10: Outside the bee-toxicity, transferable molecular-toxicity, or molecular-QML scope of the three searches. | S10: RSC Advances | T10: https://doi.org/10.1039/c9ra09475j | U10: https://www.scopus.com/pages/publications/85079233773?origin=resultslist | V10: All Open Access; Gold Open Access; Green Open Access
A11: 10 | B11: 2025 | C11: Developing Computational Toxicology Models to Assess the Risk of Environmental Pollutants on Ecosystem Health | D11: Bee toxicity ML | Molecular toxicity ML | E11: Yes | F11: Core | G11: Medium | H11: Transferable classical molecular toxicity / ecotoxicity ML | I11: ML / QSAR | J11: Chemical / molecular toxicity | K11: Predictive modeling / methodology | L11: NR in supplied metadata | M11: NR in supplied metadata | N11: Random Forest; SVM/SVR; Neural network; kNN | O11: NR in supplied metadata | P11: The models achieved accuracies of 69%, 80%, 71%, and 96% respectively, highlighting the superior performance of the Random Forest approach when compared with other traditional models. | Q11: No | R11: Transferable methodology for strengthening classical baselines, representation analysis, validation, interpretability or generalization beyond the base bee-toxicity study. | S11: INDISCON 2025 - IEEE 6th India Council International Subsections Conference, Proceedings | T11: https://doi.org/10.1109/INDISCON66021.2025.11254833 | U11: https://www.scopus.com/pages/publications/105030159313?origin=resultslist
A12: 11 | B12: 2020 | C12: Predicting the acute ecotoxicity of chemical substances by machine learning using graph theory | D12: Bee toxicity ML | Molecular toxicity ML | E12: Yes | F12: Core | G12: Medium | H12: Transferable classical molecular toxicity / ecotoxicity ML | I12: ML / QSAR | J12: Chemical ecotoxicity | K12: Classification / regression | L12: NR in supplied metadata | M12: MACCS | N12: Linear Regression | O12: NR in supplied metadata | P12: Due to empirical classification, the prediction accuracy does not improve even if new ecotoxicity test data are added. | Q12: No | R12: Transferable methodology for strengthening classical baselines, representation analysis, validation, interpretability or generalization beyond the base bee-toxicity study. | S12: Chemosphere | T12: https://doi.org/10.1016/j.chemosphere.2019.124604 | U12: https://www.scopus.com/pages/publications/85071052153?origin=resultslist
A13: 12 | B13: 2019 | C13: Could deep learning in neural networks improve the QSAR models? | D13: Bee toxicity ML | Molecular toxicity ML | E13: Yes | F13: Core | G13: Medium | H13: Transferable classical molecular toxicity / ecotoxicity ML | I13: DL / neural network | J13: Mutagenicity / Ames | K13: Classification | L13: NR in supplied metadata | M13: Molecular descriptors; Molecular graphs; SMILES | N13: Neural network | O13: NR in supplied metadata | P13: Results of our networks, trained on a ~20K molecule dataset with Ames test experimental values, match or even outperform the current state of the art. | Q13: No | R13: Transferable methodology for strengthening classical baselines, representation analysis, validation, interpretability or generalization beyond the base bee-toxicity study. | S13: SAR and QSAR in Environmental Research | T13: https://doi.org/10.1080/1062936X.2019.1650827 | U13: https://www.scopus.com/pages/publications/85071324022?origin=resultslist
A14: 13 | B14: 2016 | C14: QSAR modeling of tox21 challenge stress response and nuclear receptor signaling toxicity assays | D14: Bee toxicity ML | E14: No | F14: Exclude | G14: Low | H14: Search noise / outside scope | I14: DL / neural network | J14: Chemical / molecular toxicity | K14: Predictive modeling / methodology | L14: Tox21 | M14: Molecular descriptors | N14: Random Forest; Neural network | O14: NR in supplied metadata | P14: All of our models were statistically significant for each of the 12 assays with the balanced accuracy in the range between 0.58 and 0.82. | Q14: No | R14: Outside the bee-toxicity, transferable molecular-toxicity, or molecular-QML scope of the three searches. | S14: Frontiers in Environmental Science | T14: https://doi.org/10.3389/fenvs.2016.00003 | U14: https://www.scopus.com/pages/publications/85014162342?origin=resultslist | V14: All Open Access; Gold Open Access
A15: 14 | B15: 2020 | C15: Predicting acute contact toxicity of organic binary mixtures in honey bees (A. mellifera) through innovative QSAR models | D15: Bee toxicity ML | E15: No | F15: Core | G15: High | H15: Direct honey-bee toxicity ML / QSAR | I15: ML / QSAR | J15: Honey-bee pesticide mixture toxicity | K15: Classification / regression | L15: NR in supplied metadata | M15: Molecular graphs; SMILES | N15: ML / QSAR model | O15: NR in supplied metadata | P15: The two regression models were validated for their reliability and robustness (R2 = 0.89, CCC = 0.92, Q2 = 0.81; R2 = 0.87, CCC = 0.89, Q2 = 0.75). | Q15: No | R15: Direct prior art for the target endpoint; useful for comparing datasets, molecular representations, classical baselines, validation and reported limitations. | S15: Science of the Total Environment | T15: https://doi.org/10.1016/j.scitotenv.2019.135302 | U15: https://www.scopus.com/pages/publications/85076609141?origin=resultslist | V15: All Open Access; Bronze Open Access; Green Open Access
A16: 15 | B16: 2024 | C16: Using honey bee flight activity data and a deep learning model as a toxicovigilance tool | D16: Bee toxicity ML | E16: No | F16: Core | G16: High | H16: Direct honey-bee toxicity ML / QSAR | I16: DL / neural network | J16: Honey-bee health / toxicity-related outcome | K16: Classification | L16: NR in supplied metadata | M16: NR in supplied metadata | N16: Neural network | O16: NR in supplied metadata | P16: However, the highest classification accuracy of 99%, a Cohen Kappa of 0.9766, a precision of 0.99, a recall of 0.99, and an F1-score of 0.99 was achieved with the model trained on 25 days of activity data, signifying near-perfect classification ability. | Q16: No | R16: Direct prior art for the target endpoint; useful for comparing datasets, molecular representations, classical baselines, validation and reported limitations. | S16: Ecological Informatics | T16: https://doi.org/10.1016/j.ecoinf.2024.102653 | U16: https://www.scopus.com/pages/publications/85194578152?origin=resultslist | V16: All Open Access; Gold Open Access; Green Open Access
A17: 16 | B17: 2024 | C17: Comprehensive hepatotoxicity prediction: ensemble model integrating machine learning and deep learning | D17: Bee toxicity ML | Molecular toxicity ML | E17: Yes | F17: Core | G17: High | H17: Transferable classical molecular toxicity / ecotoxicity ML | I17: DL / neural network | J17: Hepatotoxicity / liver toxicity | K17: Review / guidance | L17: 2588 chemicals | M17: Molecular fingerprints; Molecular descriptors | N17: Ensemble | O17: External test; Cross-validation | P17: Results: The voting ensemble classifier emerged as the optimal model, achieving an excellent prediction accuracy of 80.26%, AUC of 82.84%, and recall of over 93% followed by bagging and stacking ensemble classifiers method. | Q17: No | R17: Transferable methodology for strengthening classical baselines, representation analysis, validation, interpretability or generalization beyond the base bee-toxicity study. | S17: Frontiers in Pharmacology | T17: https://doi.org/10.3389/fphar.2024.1441587 | U17: https://www.scopus.com/pages/publications/85203458932?origin=resultslist | V17: All Open Access; Gold Open Access; Green Open Access
A18: 17 | B18: 2025 | C18: A Comparative Evaluation of Machine Learning and Deep Graph Learning for Chemical Ecotoxicological Prediction | D18: Bee toxicity ML | Molecular toxicity ML | E18: Yes | F18: Core | G18: Medium | H18: Transferable classical molecular toxicity / ecotoxicity ML | I18: DL / neural network | J18: Chemical ecotoxicity | K18: Predictive modeling / methodology | L18: NR in supplied metadata | M18: Morgan fingerprints; MACCS; Molecular fingerprints; Molecular graphs / GNN representation | N18: GNN; GCN; Neural network | O18: NR in supplied metadata | P18: In the same-species predictions, GCN models achieved the highest values of area under the ROC curve (AUC), ranging between 0.982 and 0.992. | Q18: No | R18: Transferable methodology for strengthening classical baselines, representation analysis, validation, interpretability or generalization beyond the base bee-toxicity study. | S18: ACS Omega | T18: https://doi.org/10.1021/acsomega.5c03753 | U18: https://www.scopus.com/pages/publications/105014545066?origin=resultslist | V18: All Open Access; Gold Open Access; Green Open Access
A19: 18 | B19: 2026 | C19: A QSAR-machine learning hybrid model for predicting the ecotoxicity of soil organic compounds and deriving thresholds | D19: Bee toxicity ML | Molecular toxicity ML | E19: Yes | F19: Core | G19: High | H19: Transferable classical molecular toxicity / ecotoxicity ML | I19: Classical ML with quantum-chemical information | J19: Chemical ecotoxicity | K19: Regression | L19: 305 compounds | M19: Molecular descriptors; Molecular graphs | N19: Random Forest; XGBoost; CatBoost | O19: External validation | P19: The ecological thresholds were derived via species sensitivity distribution (SSD). | Q19: Quantum chemistry / QM features; not QML | R19: Transferable methodology for strengthening classical baselines, representation analysis, validation, interpretability or generalization beyond the base bee-toxicity study. | S19: Journal of Cleaner Production | T19: https://doi.org/10.1016/j.jclepro.2026.147869 | U19: https://www.scopus.com/pages/publications/105030933470?origin=resultslist
A20: 19 | B20: 2025 | C20: Spatial non-targeted screening and machine learning-based risk assessment of organic pollutants in honey from Bhakkar District, Pakistan | D20: Bee toxicity ML | E20: No | F20: Exclude | G20: Low | H20: Search noise / outside scope | I20: ML / QSAR | J20: Mutagenicity / Ames | K20: Regression | L20: NR in supplied metadata | M20: NR in supplied metadata | N20: CatBoost | O20: NR in supplied metadata | P20: To predict HRI values and identify contributing factors, supervised machine learning (ML) models were developed and optimized using the Optuna framework, with the Categorical Boosting (CatBoost) model achieving the highest predictive accuracy (R2 = 91.31%, RMSE = 0.125, MAE = 0.079). | Q20: No | R20: Outside the bee-toxicity, transferable molecular-toxicity, or molecular-QML scope of the three searches. | S20: Journal of Environmental Chemical Engineering | T20: https://doi.org/10.1016/j.jece.2025.118509 | U20: https://www.scopus.com/pages/publications/105015138470?origin=resultslist | V20: All Open Access; Hybrid Gold Open Access
A21: 20 | B21: 2021 | C21: Multi-biomarker approach and IBR index to evaluate the effects of different contaminants on the ecotoxicological status of Apis mellifera | D21: Bee toxicity ML | E21: No | F21: Supporting | G21: Medium | H21: Honey-bee toxicology / problem context | I21: Non-ML / experimental or contextual | J21: Honey-bee / Apis mellifera toxicity | K21: Experimental / risk-assessment study | L21: NR in supplied metadata | M21: NR in supplied metadata | N21: NR in supplied metadata | O21: NR in supplied metadata | P21: NR in supplied abstract | Q21: No | R21: Useful for problem justification, endpoint interpretation, exposure mechanisms, species sensitivity or limitations not captured by structure-only ML. | S21: Ecotoxicology and Environmental Safety | T21: https://doi.org/10.1016/j.ecoenv.2020.111486 | U21: https://www.scopus.com/pages/publications/85094624286?origin=resultslist | V21: All Open Access; Green Open Access; Hybrid Gold Open Access
A22: 21 | B22: 2025 | C22: Poisoning due to Spinosad in honey bees: toxicological report | D22: Bee toxicity ML | E22: No | F22: Supporting | G22: Medium | H22: Honey-bee toxicology / problem context | I22: Non-ML / experimental or contextual | J22: Honey-bee pesticide mixture toxicity | K22: Classification | L22: NR in supplied metadata | M22: NR in supplied metadata | N22: NR in supplied metadata | O22: NR in supplied metadata | P22: NR in supplied abstract | Q22: No | R22: Useful for problem justification, endpoint interpretation, exposure mechanisms, species sensitivity or limitations not captured by structure-only ML. | S22: Journal of Apicultural Research | T22: https://doi.org/10.1080/00218839.2024.2425913 | U22: https://www.scopus.com/pages/publications/85210160671?origin=resultslist
A23: 22 | B23: 2026 | C23: Interpretable multi-modality consensus QSAR framework: integrating machine and deep learning for enhanced multi-endpoint toxicity assessment | D23: Bee toxicity ML | Molecular toxicity ML | E23: Yes | F23: Core | G23: High | H23: Transferable classical molecular toxicity / ecotoxicity ML | I23: DL / neural network | J23: Mutagenicity / Ames | K23: Predictive modeling / methodology | L23: 160 compounds | M23: Molecular descriptors | N23: Random Forest; Gradient Boosting; SVM/SVR; Neural network | O23: Cross-validation; Applicability-domain analysis | P23: Models for each descriptor–algorithm combination were optimized using 10-fold cross-validation, and top-performing models were combined into weighted multi-modality consensus predictors based on cross-validated area under the receiver operating characteristic curve (AUC) weights. | Q23: No | R23: Transferable methodology for strengthening classical baselines, representation analysis, validation, interpretability or generalization beyond the base bee-toxicity study. | S23: Toxicology Mechanisms and Methods | T23: https://doi.org/10.1080/15376516.2026.2643659 | U23: https://www.scopus.com/pages/publications/105033707008?origin=resultslist
A24: 23 | B24: 2025 | C24: Toxicity of the essential oils of Eugenia uniflora and Pogostemon cablin on field bees of Africanized Apis mellifera L., 1758 (Hymenoptera: Apidae) | D24: Bee toxicity ML | E24: No | F24: Supporting | G24: Medium | H24: Honey-bee toxicology / problem context | I24: Non-ML / experimental or contextual | J24: Honey-bee / Apis mellifera toxicity | K24: Experimental / risk-assessment study | L24: NR in supplied metadata | M24: NR in supplied metadata | N24: NR in supplied metadata | O24: NR in supplied metadata | P24: NR in supplied abstract | Q24: No | R24: Useful for problem justification, endpoint interpretation, exposure mechanisms, species sensitivity or limitations not captured by structure-only ML. | S24: Journal of Asia-Pacific Entomology | T24: https://doi.org/10.1016/j.aspen.2025.102452 | U24: https://www.scopus.com/pages/publications/105014108723?origin=resultslist
A25: 24 | B25: 2026 | C25: Evaluating machine learning models for predicting pesticide toxicity to honey bees | D25: Bee toxicity ML | E25: No | F25: Core | G25: High | H25: Direct honey-bee toxicity ML / QSAR | I25: DL / neural network | J25: Honey-bee / Apis mellifera toxicity | K25: Predictive modeling / methodology | L25: ApisTox | M25: Molecular fingerprints; Molecular graphs / GNN representation | N25: GNN; Neural network | O25: Cross-validation | P25: NR in supplied abstract | Q25: No | R25: Direct prior art for the target endpoint; useful for comparing datasets, molecular representations, classical baselines, validation and reported limitations. | S25: Ecotoxicology and Environmental Safety | T25: https://doi.org/10.1016/j.ecoenv.2026.119869 | U25: https://www.scopus.com/pages/publications/105031117980?origin=resultslist | V25: All Open Access; Gold Open Access; Green Open Access
A26: 25 | B26: 2017 | C26: Predicting acute contact toxicity of pesticides in honeybees (Apis mellifera) through a k-nearest neighbor model | D26: Bee toxicity ML | E26: No | F26: Core | G26: High | H26: Direct honey-bee toxicity ML / QSAR | I26: ML / QSAR | J26: Honey-bee / Apis mellifera toxicity | K26: Regression | L26: 256 pesticides | M26: NR in supplied metadata | N26: kNN | O26: NR in supplied metadata | P26: The k-NN models were validated with good prediction, with an accuracy of 70% for all compounds and of 65% for highly toxic compounds, suggesting that they might reliably predict the toxicity of structurally diverse pesticides and could be used to screen and prioritise new pesticides. | Q26: No | R26: Direct prior art for the target endpoint; useful for comparing datasets, molecular representations, classical baselines, validation and reported limitations. | S26: Chemosphere | T26: https://doi.org/10.1016/j.chemosphere.2016.09.092 | U26: https://www.scopus.com/pages/publications/84989287587?origin=resultslist
A27: 26 | B27: 2024 | C27: Leveraging In Silico Structure-Activity Models to Predict Acute Honey Bee (Apis mellifera) Toxicity for Agrochemicals | D27: Bee toxicity ML | E27: No | F27: Core | G27: High | H27: Direct honey-bee toxicity ML / QSAR | I27: ML / QSAR | J27: Honey-bee / Apis mellifera toxicity | K27: Classification | L27: 1542 compounds | M27: NR in supplied metadata | N27: Neural network | O27: NR in supplied metadata | P27: Bee toxicity data from 1542 compounds were used to develop models; the sensitivity and specificity of the best model were 0.90 and 0.91, respectively. | Q27: No | R27: Direct prior art for the target endpoint; useful for comparing datasets, molecular representations, classical baselines, validation and reported limitations. | S27: Journal of Agricultural and Food Chemistry | T27: https://doi.org/10.1021/acs.jafc.4c02518 | U27: https://www.scopus.com/pages/publications/85203802131?origin=resultslist
A28: 27 | B28: 2026 | C28: Predicting aquatic toxicity of organic compounds using the ML-DL-ens model: An integrated approach of machine learning and deep learning | D28: Bee toxicity ML | E28: No | F28: Exclude | G28: Low | H28: Search noise / outside scope | I28: DL / neural network | J28: Chemical ecotoxicity | K28: Regression | L28: NR in supplied metadata | M28: NR in supplied metadata | N28: Random Forest; Gradient Boosting; SVM/SVR; Neural network; kNN | O28: Cross-validation | P28: Although classic machine learning methods have shown potential in toxicity prediction, their limitations - including reliance on manual feature engineering, poor generalization ability in different chemical spaces, and sensitivity to data noise - have reduced their reliability in practical applications. | Q28: No | R28: Outside the bee-toxicity, transferable molecular-toxicity, or molecular-QML scope of the three searches. | S28: Ecotoxicology and Environmental Safety | T28: https://doi.org/10.1016/j.ecoenv.2026.119803 | U28: https://www.scopus.com/pages/publications/105029270030?origin=resultslist | V28: All Open Access; Gold Open Access
A29: 28 | B29: 2022 | C29: Classifying the toxicity of pesticides to honey bees via support vector machines with random walk graph kernels | D29: Bee toxicity ML | E29: No | F29: Core | G29: High | H29: Direct honey-bee toxicity ML / QSAR | I29: ML / QSAR | J29: Honey-bee / Apis mellifera toxicity | K29: Classification | L29: 382 molecules | M29: MACCS; Molecular fingerprints; Molecular graphs | N29: SVM/SVR | O29: NR in supplied metadata | P29: The L-RWGK-SVM achieves an accuracy, precision, recall, and F1 score (mean over 2000 runs) of 0.81, 0.68, 0.71, and 0.69, respectively, on the test data set - with L = 4 being the mode optimal walk length. | Q29: No | R29: Direct prior art for the target endpoint; useful for comparing datasets, molecular representations, classical baselines, validation and reported limitations. | S29: Journal of Chemical Physics | T29: https://doi.org/10.1063/5.0090573 | U29: https://www.scopus.com/pages/publications/85135008849?origin=resultslist
A30: 29 | B30: 2020 | C30: Multi-scale QSAR approach for simultaneous modeling of ecotoxic effects of pesticides | D30: Bee toxicity ML | E30: No | F30: Exclude | G30: Low | H30: Search noise / outside scope | I30: ML / QSAR | J30: Chemical ecotoxicity | K30: Predictive modeling / methodology | L30: NR in supplied metadata | M30: Molecular descriptors | N30: Neural network | O30: NR in supplied metadata | P30: NR in supplied abstract | Q30: No | R30: Outside the bee-toxicity, transferable molecular-toxicity, or molecular-QML scope of the three searches. | S30: Methods in Pharmacology and Toxicology | T30: https://doi.org/10.1007/978-1-0716-0150-1_26 | U30: https://www.scopus.com/pages/publications/85078080395?origin=resultslist
A31: 30 | B31: 2026 | C31: Multi-biomarker assessment of Apis mellifera as a sentinel of environmental stress: A two-year field study across diverse land-use gradients in Tuscany (Italy) | D31: Bee toxicity ML | E31: No | F31: Supporting | G31: Medium | H31: Honey-bee toxicology / problem context | I31: Non-ML / experimental or contextual | J31: Honey-bee / Apis mellifera toxicity | K31: Experimental / risk-assessment study | L31: NR in supplied metadata | M31: NR in supplied metadata | N31: NR in supplied metadata | O31: NR in supplied metadata | P31: NR in supplied abstract | Q31: No | R31: Useful for problem justification, endpoint interpretation, exposure mechanisms, species sensitivity or limitations not captured by structure-only ML. | S31: Environmental Research | T31: https://doi.org/10.1016/j.envres.2026.125038 | U31: https://www.scopus.com/pages/publications/105042261289?origin=resultslist | V31: All Open Access; Green Open Access; Hybrid Gold Open Access
A32: 31 | B32: 2025 | C32: Predicting Pesticide LC50 Toxicity Using Convolutional Neural Networks and Dragonfly-Support Vector Machine Methods with Quantitative Structure-Activity Relationship and 2D Molecular Fingerprints: A Case Study on Oncorhynchus Mykiss | D32: Bee toxicity ML | Molecular toxicity ML | E32: Yes | F32: Core | G32: High | H32: Transferable classical molecular toxicity / ecotoxicity ML | I32: DL / neural network | J32: Chemical ecotoxicity | K32: Regression | L32: 200 pesticides | M32: Morgan fingerprints; Molecular fingerprints; Molecular descriptors | N32: SVM/SVR; CNN; Neural network | O32: NR in supplied metadata | P32: Model 3 presents the best performance by achieving high predictive global accuracy in terms of RMSE of 0.1755, R² of 0.9860, AARD of 2.9765% and MAE of 0.0590. | Q32: No | R32: Transferable methodology for strengthening classical baselines, representation analysis, validation, interpretability or generalization beyond the base bee-toxicity study. | S32: Chemistry Africa | T32: https://doi.org/10.1007/s42250-025-01239-7 | U32: https://www.scopus.com/pages/publications/86000347183?origin=resultslist
A33: 32 | B33: 2025 | C33: Utilizing Machine Learning Algorithms for Accurate Prediction of Nanomat erials Cytotoxicity | D33: Bee toxicity ML | E33: No | F33: Exclude | G33: Low | H33: Search noise / outside scope | I33: ML / QSAR | J33: Cytotoxicity | K33: Predictive modeling / methodology | L33: NR in supplied metadata | M33: Molecular descriptors | N33: Random Forest; kNN | O33: External validation | P33: If built correctly, these models can predict NMs' toxicity with the highest accuracy and reliability. | Q33: No | R33: Outside the bee-toxicity, transferable molecular-toxicity, or molecular-QML scope of the three searches. | S33: Letters in Applied NanoBioScience | T33: https://doi.org/10.33263/LIANBS143.134 | U33: https://www.scopus.com/pages/publications/105019986249?origin=resultslist
A34: 33 | B34: 2026 | C34: Life Cycle Thinking in Early Drug Discovery: Reducing Environmental Impact and Animal Testing via Interpretable Machine Learning- and Chemometrics-Based Oral Acute Toxicity Screening | D34: Bee toxicity ML | E34: No | F34: Exclude | G34: Low | H34: Search noise / outside scope | I34: DL / neural network | J34: Acute chemical toxicity | K34: Predictive modeling / methodology | L34: 1150 compounds | M34: NR in supplied metadata | N34: Read-across; RASAR | O34: External validation; Scaffold-based evaluation | P34: NR in supplied abstract | Q34: No | R34: Outside the bee-toxicity, transferable molecular-toxicity, or molecular-QML scope of the three searches. | S34: ACS Sustainable Chemistry and Engineering | T34: https://doi.org/10.1021/acssuschemeng.6c03787 | U34: https://www.scopus.com/pages/publications/105041915734?origin=resultslist
A35: 34 | B35: 2020 | C35: Image Based Liver Toxicity Prediction | D35: Bee toxicity ML | E35: No | F35: Exclude | G35: Low | H35: Search noise / outside scope | I35: DL / neural network | J35: Hepatotoxicity / liver toxicity | K35: Predictive modeling / methodology | L35: Tox21 | M35: NR in supplied metadata | N35: CNN; Neural network | O35: NR in supplied metadata | P35: and obtain a sensitivity of 0.79 and a specificity of 0.52. | Q35: No | R35: Outside the bee-toxicity, transferable molecular-toxicity, or molecular-QML scope of the three searches. | S35: Journal of Chemical Information and Modeling | T35: https://doi.org/10.1021/acs.jcim.9b00713 | U35: https://www.scopus.com/pages/publications/85079671841?origin=resultslist | V35: All Open Access; Hybrid Gold Open Access
A36: 35 | B36: 2025 | C36: New generation of QSAR modeling for bee safety: predicting toxicity using graph neural networks and apistox data | D36: Bee toxicity ML | Molecular toxicity ML | E36: Yes | F36: Core | G36: High | H36: Direct honey-bee toxicity ML / QSAR | I36: DL / neural network | J36: Honey-bee / Apis mellifera toxicity | K36: Predictive modeling / methodology | L36: ApisTox | M36: Molecular graphs; Molecular graphs / GNN representation; SMILES | N36: GNN; Neural network | O36: Cross-validation | P36: The model achieved an average AUC-ROC of 0.76 on the test set and 0.97 on the training set, with low standard deviations (± 0.03), indicating consistent performance across cross-validation folds. | Q36: No | R36: Direct prior art for the target endpoint; useful for comparing datasets, molecular representations, classical baselines, validation and reported limitations. | S36: Ecotoxicology | T36: https://doi.org/10.1007/s10646-025-02970-0 | U36: https://www.scopus.com/pages/publications/105016759455?origin=resultslist
A37: 36 | B37: 2022 | C37: Toxicological assessment of agrochemicals in bees using machine learning tools | D37: Bee toxicity ML | E37: No | F37: Exclude | G37: Low | H37: Search noise / outside scope | I37: ML / QSAR | J37: Chemical ecotoxicity | K37: Predictive modeling / methodology | L37: NR in supplied metadata | M37: NR in supplied metadata | N37: ML / QSAR model | O37: NR in supplied metadata | P37: The ML algorithms achieved a higher accuracy (up to 91%) in identifying agrochemical contamination. | Q37: No | R37: Outside the bee-toxicity, transferable molecular-toxicity, or molecular-QML scope of the three searches. | S37: Journal of Hazardous Materials | T37: https://doi.org/10.1016/j.jhazmat.2021.127344 | U37: https://www.scopus.com/pages/publications/85116067761?origin=resultslist
A38: 37 | B38: 2025 | C38: In silico assessment of the impact of pesticides commonly used in fruit orchards on Apis mellifera (Linnaeus, 1758) (Hymenoptera: Apidae): implications for pollinator health | D38: Bee toxicity ML | E38: No | F38: Supporting | G38: Medium | H38: Honey-bee toxicology / problem context | I38: Non-ML / experimental or contextual | J38: Honey-bee / Apis mellifera toxicity | K38: Experimental / risk-assessment study | L38: NR in supplied metadata | M38: NR in supplied metadata | N38: NR in supplied metadata | O38: NR in supplied metadata | P38: NR in supplied abstract | Q38: No | R38: Useful for problem justification, endpoint interpretation, exposure mechanisms, species sensitivity or limitations not captured by structure-only ML. | S38: Journal of Environmental Science and Health - Part B Pesticides, Food Contaminants, and Agricultural Wastes | T38: https://doi.org/10.1080/03601234.2025.2588075 | U38: https://www.scopus.com/pages/publications/105021971558?origin=resultslist
A39: 38 | B39: 2026 | C39: Combined toxic impacts of imidacloprid and epoxiconazole on Apis mellifera L. and the underlying mechanism | D39: Bee toxicity ML | E39: No | F39: Supporting | G39: Medium | H39: Honey-bee toxicology / problem context | I39: Non-ML / experimental or contextual | J39: Honey-bee pesticide mixture toxicity | K39: Experimental / risk-assessment study | L39: NR in supplied metadata | M39: NR in supplied metadata | N39: NR in supplied metadata | O39: NR in supplied metadata | P39: NR in supplied abstract | Q39: No | R39: Useful for problem justification, endpoint interpretation, exposure mechanisms, species sensitivity or limitations not captured by structure-only ML. | S39: Pesticide Biochemistry and Physiology | T39: https://doi.org/10.1016/j.pestbp.2026.107226 | U39: https://www.scopus.com/pages/publications/105042923227?origin=resultslist
A40: 39 | B40: 2024 | C40: A comprehensive machine learning-based models for predicting mixture toxicity of azole fungicides toward algae (Auxenochlorella pyrenoidosa) | D40: Bee toxicity ML | E40: No | F40: Supporting | G40: Medium | H40: Quantum chemistry + classical ML / molecular modeling | I40: Classical ML with quantum-chemical information | J40: Chemical ecotoxicity | K40: Regression | L40: NR in supplied metadata | M40: Molecular descriptors | N40: Random Forest; XGBoost; Gradient Boosting; SVM/SVR; Neural network; kNN | O40: Cross-validation | P40: The results indicated that models employing concentration addition (CA), independent action (IA), and molecular descriptors (MD) as variables demonstrated superior predictive abilities. | Q40: Quantum chemistry / QM features; not QML | R40: Useful as adjacent molecular representation work, but quantum-chemical descriptors/calculations are not quantum machine learning. | S40: Environment International | T40: https://doi.org/10.1016/j.envint.2024.109162 | U40: https://www.scopus.com/pages/publications/85210281491?origin=resultslist | V40: All Open Access; Gold Open Access; Green Open Access
A41: 40 | B41: 2023 | C41: Deep learning using molecular image of chemical structure | D41: Bee toxicity ML | Molecular toxicity ML | E41: Yes | F41: Core | G41: High | H41: Transferable classical molecular toxicity / ecotoxicity ML | I41: DL / neural network | J41: Chemical / molecular toxicity | K41: Review / guidance | L41: NR in supplied metadata | M41: Molecular descriptors; Molecular images; 3D molecular information | N41: ML / QSAR model | O41: NR in supplied metadata | P41: NR in supplied abstract | Q41: No | R41: Transferable methodology for strengthening classical baselines, representation analysis, validation, interpretability or generalization beyond the base bee-toxicity study. | S41: Cheminformatics, QSAR and Machine Learning Applications for Novel Drug Development | T41: https://doi.org/10.1016/B978-0-443-18638-7.00005-0 | U41: https://www.scopus.com/pages/publications/85163448577?origin=resultslist
A42: 41 | B42: 2017 | C42: Comparative toxicity of pesticides and environmental contaminants in bees: Are honey bees a useful proxy for wild bee species? | D42: Bee toxicity ML | E42: No | F42: Supporting | G42: Medium | H42: Honey-bee toxicology / problem context | I42: Non-ML / experimental or contextual | J42: Honey-bee pesticide mixture toxicity | K42: Classification / regression | L42: NR in supplied metadata | M42: NR in supplied metadata | N42: NR in supplied metadata | O42: NR in supplied metadata | P42: Historically the honey bee (Apis mellifera spp.) has been used as an ‘indicator’ species for ‘standard’ ecotoxicological testing but it has been suggested that it is not always a good proxy for other types of eusocial and solitary bees because of species differences in autecology and sensitivity to various stressors. | Q42: No | R42: Useful for problem justification, endpoint interpretation, exposure mechanisms, species sensitivity or limitations not captured by structure-only ML. | S42: Science of the Total Environment | T42: https://doi.org/10.1016/j.scitotenv.2016.10.180 | U42: https://www.scopus.com/pages/publications/85003945078?origin=resultslist | V42: All Open Access; Bronze Open Access
A43: 42 | B43: 2024 | C43: Architecture and potential roles of a delta-class glutathione S-transferase in protecting honey bee from agrochemicals | D43: Bee toxicity ML | E43: No | F43: Supporting | G43: Medium | H43: Honey-bee toxicology / problem context | I43: Non-ML / experimental or contextual | J43: Honey-bee / Apis mellifera toxicity | K43: Experimental / risk-assessment study | L43: NR in supplied metadata | M43: 3D molecular information | N43: NR in supplied metadata | O43: NR in supplied metadata | P43: NR in supplied abstract | Q43: No | R43: Useful for problem justification, endpoint interpretation, exposure mechanisms, species sensitivity or limitations not captured by structure-only ML. | S43: Chemosphere | T43: https://doi.org/10.1016/j.chemosphere.2023.141089 | U43: https://www.scopus.com/pages/publications/85181771235?origin=resultslist | V43: All Open Access; Bronze Open Access; Green Open Access
A44: 43 | B44: 2022 | C44: Ecotoxicological risk assessment of organic compounds against various aquatic and terrestrial species: application of interspecies i-QSTTR and species sensitivity distribution techniques† | D44: Bee toxicity ML | E44: No | F44: Exclude | G44: Low | H44: Search noise / outside scope | I44: ML / QSAR | J44: Chemical ecotoxicity | K44: Regression | L44: NR in supplied metadata | M44: Molecular descriptors; Molecular graphs | N44: ML / QSAR model | O44: Applicability-domain analysis | P44: In silico techniques employed in hazard assessment have evolved for years starting from simple quantitative structure-activity/toxicity relationship (QSAR/QSTR) models to interspecies quantitative structure-toxicity-toxicity relationship (i-QSTTR) models and finally towards species sensitivity distributions (SSDs). | Q44: No | R44: Outside the bee-toxicity, transferable molecular-toxicity, or molecular-QML scope of the three searches. | S44: Green Chemistry | T44: https://doi.org/10.1039/d1gc04320j | U44: https://www.scopus.com/pages/publications/85127200906?origin=resultslist
A45: 44 | B45: 2017 | C45: Insights into the Molecular Basis of the Acute Contact Toxicity of Diverse Organic Chemicals in the Honey Bee | D45: Bee toxicity ML | E45: No | F45: Core | G45: High | H45: Direct honey-bee toxicity ML / QSAR | I45: ML / QSAR | J45: Honey-bee / Apis mellifera toxicity | K45: Classification / regression | L45: NR in supplied metadata | M45: Molecular fingerprints; Molecular descriptors | N45: ML / QSAR model | O45: External validation; Cross-validation | P45: NR in supplied abstract | Q45: No | R45: Direct prior art for the target endpoint; useful for comparing datasets, molecular representations, classical baselines, validation and reported limitations. | S45: Journal of Chemical Information and Modeling | T45: https://doi.org/10.1021/acs.jcim.7b00476 | U45: https://www.scopus.com/pages/publications/85039988952?origin=resultslist
A46: 45 | B46: 2026 | C46: Machine learning based assessment of the toxicity of polymeric materials to green algae as an approach to design non-toxic polymeric coatings to deter marine biofouling | D46: Bee toxicity ML | Molecular toxicity ML | E46: Yes | F46: Core | G46: Medium | H46: Transferable classical molecular toxicity / ecotoxicity ML | I46: ML / QSAR | J46: Chemical ecotoxicity | K46: Regression | L46: NR in supplied metadata | M46: Molecular descriptors | N46: ML / QSAR model | O46: NR in supplied metadata | P46: The best models were selected based on their performance on training ( R 2 train , Q 2 , RMSE ) and validation sets ( R 2 test , y -scrambling). | Q46: No | R46: Transferable methodology for strengthening classical baselines, representation analysis, validation, interpretability or generalization beyond the base bee-toxicity study. | S46: Results in Chemistry | T46: https://doi.org/10.1016/j.rechem.2025.103005 | U46: https://www.scopus.com/pages/publications/105026149047?origin=resultslist | V46: All Open Access; Gold Open Access
A47: 46 | B47: 2022 | C47: Chemometric modeling of plant protection products (PPPs) for the prediction of acute contact toxicity against honey bees (A. mellifera): A 2D-QSAR approach | D47: Bee toxicity ML | E47: No | F47: Core | G47: High | H47: Direct honey-bee toxicity ML / QSAR | I47: ML / QSAR | J47: Honey-bee / Apis mellifera toxicity | K47: Regression | L47: 709 compounds | M47: Molecular graphs | N47: ML / QSAR model | O47: External validation; Applicability-domain analysis | P47: The obtained results (R2 = 0.666, Q2 = 0.594, Q2F1 = 0.647 and Q2F2 = 0.646) determine the predictability and reliability of the developed model. | Q47: No | R47: Direct prior art for the target endpoint; useful for comparing datasets, molecular representations, classical baselines, validation and reported limitations. | S47: Journal of Hazardous Materials | T47: https://doi.org/10.1016/j.jhazmat.2021.127230 | U47: https://www.scopus.com/pages/publications/85115387479?origin=resultslist
A48: 47 | B48: 2023 | C48: Comparison of the Sensitivity of Tetragonisca angustula (Apidae-Meliponini) and Apis mellifera (Apidae-Apini) to Three Insecticides (Malathion, Imidacloprid, and Fipronil) Used in Costa Rica | D48: Bee toxicity ML | E48: No | F48: Supporting | G48: Medium | H48: Honey-bee toxicology / problem context | I48: Non-ML / experimental or contextual | J48: Honey-bee / Apis mellifera toxicity | K48: Regression | L48: NR in supplied metadata | M48: NR in supplied metadata | N48: NR in supplied metadata | O48: NR in supplied metadata | P48: Our results suggest that specific sensitivity to insecticides varies greatly among compounds and pollinator species, but the use of different representative species can facilitate the prioritization of substances regarding their risk to pollinators. | Q48: No | R48: Useful for problem justification, endpoint interpretation, exposure mechanisms, species sensitivity or limitations not captured by structure-only ML. | S48: Environmental Toxicology and Chemistry | T48: https://doi.org/10.1002/etc.5587 | U48: https://www.scopus.com/pages/publications/85150886960?origin=resultslist
A49: 48 | B49: 2020 | C49: Integrating QSAR models predicting acute contact toxicity and mode of action profiling in honey bees (A. mellifera): Data curation using open source databases, performance testing and validation | D49: Bee toxicity ML | E49: No | F49: Core | G49: High | H49: Direct honey-bee toxicity ML / QSAR | I49: ML / QSAR | J49: Honey-bee pesticide mixture toxicity | K49: Review / guidance | L49: 113 pesticides | M49: Molecular graphs | N49: ML / QSAR model | O49: NR in supplied metadata | P49: The two-category QSAR model (toxic/non-toxic; n = 411) was validated using sensitivity (=0.93), specificity (=0.85), balanced accuracy (=0.90), and Matthews correlation coefficient (MCC = 0.78) as statistical parameters. | Q49: No | R49: Direct prior art for the target endpoint; useful for comparing datasets, molecular representations, classical baselines, validation and reported limitations. | S49: Science of the Total Environment | T49: https://doi.org/10.1016/j.scitotenv.2020.139243 | U49: https://www.scopus.com/pages/publications/85085321096?origin=resultslist | V49: All Open Access; Green Open Access; Hybrid Gold Open Access
A50: 49 | B50: 2026 | C50: Honey yield prediction and neonicotinoid risk assessment utilizing a machine learning framework in smart agriculture | D50: Bee toxicity ML | E50: No | F50: Core | G50: High | H50: Direct honey-bee toxicity ML / QSAR | I50: ML / QSAR | J50: Honey-bee / Apis mellifera toxicity | K50: Classification | L50: NR in supplied metadata | M50: NR in supplied metadata | N50: SVM/SVR; Ensemble | O50: NR in supplied metadata | P50: Notably, our proposed voting classifier (AgriBuzzEnsemble), which synergistically fuses Support Vector Machine (SVM) and Gaussian Naive Bayes (GNB), surpassed all baseline models, showcasing robust accuracy of 98%, a Matthews Correlation Coefficient (MCC) of 0.9751, a specificity of 0.9917, and an ROC AUC of 0.9985. | Q50: No | R50: Direct prior art for the target endpoint; useful for comparing datasets, molecular representations, classical baselines, validation and reported limitations. | S50: Scientific Reports | T50: https://doi.org/10.1038/s41598-026-44811-y | U50: https://www.scopus.com/pages/publications/105040603650?origin=resultslist | V50: All Open Access; Gold Open Access; Green Open Access
A51: 50 | B51: 2023 | C51: Applying Artificial Neural Networks to Oxidative Stress Biomarkers in Forager Honey Bees (Apis mellifera) for Ecological Assessment | D51: Bee toxicity ML | E51: No | F51: Core | G51: High | H51: Direct honey-bee toxicity ML / QSAR | I51: ML / QSAR | J51: Honey-bee / Apis mellifera toxicity | K51: Predictive modeling / methodology | L51: NR in supplied metadata | M51: NR in supplied metadata | N51: Neural network | O51: NR in supplied metadata | P51: NR in supplied abstract | Q51: No | R51: Direct prior art for the target endpoint; useful for comparing datasets, molecular representations, classical baselines, validation and reported limitations. | S51: Toxics | T51: https://doi.org/10.3390/toxics11080661 | U51: https://www.scopus.com/pages/publications/85169152009?origin=resultslist | V51: All Open Access; Gold Open Access; Green Open Access
A52: 51 | B52: 2021 | C52: Ecotoxicological read-across models for predicting acute toxicity of freshly dispersed versus medium-aged NMs to Daphnia magna | D52: Bee toxicity ML | E52: No | F52: Exclude | G52: Low | H52: Search noise / outside scope | I52: ML / QSAR | J52: Chemical ecotoxicity | K52: Review / guidance | L52: NR in supplied metadata | M52: NR in supplied metadata | N52: Read-across | O52: NR in supplied metadata | P52: NR in supplied abstract | Q52: No | R52: Outside the bee-toxicity, transferable molecular-toxicity, or molecular-QML scope of the three searches. | S52: Chemosphere | T52: https://doi.org/10.1016/j.chemosphere.2021.131452 | U52: https://www.scopus.com/pages/publications/85109535295?origin=resultslist | V52: All Open Access; Green Open Access; Hybrid Gold Open Access
A53: 52 | B53: 2021 | C53: In silico prediction of chemical acute contact toxicity on honey bees via machine learning methods | D53: Bee toxicity ML | E53: No | F53: Core | G53: High | H53: Direct honey-bee toxicity ML / QSAR | I53: ML / QSAR | J53: Honey-bee / Apis mellifera toxicity | K53: Classification / regression | L53: NR in supplied metadata | M53: Molecular fingerprints | N53: SVM/SVR; CNN; Neural network | O53: Applicability-domain analysis | P53: NR in supplied abstract | Q53: No | R53: Direct prior art for the target endpoint; useful for comparing datasets, molecular representations, classical baselines, validation and reported limitations. | S53: Toxicology in Vitro | T53: https://doi.org/10.1016/j.tiv.2021.105089 | U53: https://www.scopus.com/pages/publications/85099576224?origin=resultslist
A54: 53 | B54: 2026 | C54: Machine learning modeling of acute inhalation toxicity using an RFA-RFR framework, supported by explainable AI and SALI-based activity cliff analysis | D54: Bee toxicity ML | Molecular toxicity ML | E54: Yes | F54: Core | G54: High | H54: Transferable classical molecular toxicity / ecotoxicity ML | I54: ML / QSAR | J54: Chemical / molecular toxicity | K54: Regression | L54: 552 molecules | M54: Molecular descriptors; 3D molecular information | N54: Random Forest | O54: Cross-validation | P54: Importantly, benchmarking against previous QSAR models for inhalation toxicity shows improved predictive accuracy and broader chemical applicability. | Q54: No | R54: Transferable methodology for strengthening classical baselines, representation analysis, validation, interpretability or generalization beyond the base bee-toxicity study. | S54: Journal of Pharmacological and Toxicological Methods | T54: https://doi.org/10.1016/j.vascn.2026.108426 | U54: https://www.scopus.com/pages/publications/105039775493?origin=resultslist
A55: 54 | B55: 2025 | C55: Mixture of experts for multitask learning in cardiotoxicity assessment | D55: Bee toxicity ML | E55: No | F55: Exclude | G55: Low | H55: Search noise / outside scope | I55: ML / QSAR | J55: Cardiotoxicity | K55: Predictive modeling / methodology | L55: NR in supplied metadata | M55: NR in supplied metadata | N55: Neural network | O55: Holdout test | P55: The best developed model achieved a balanced accuracy of 78%, a sensitivity of 80%, and a specificity of 76% across all endpoints in the holdout set. | Q55: No | R55: Outside the bee-toxicity, transferable molecular-toxicity, or molecular-QML scope of the three searches. | S55: Journal of Cheminformatics | T55: https://doi.org/10.1186/s13321-025-01072-7 | U55: https://www.scopus.com/pages/publications/105014728209?origin=resultslist | V55: All Open Access; Gold Open Access; Green Open Access
A56: 55 | B56: 2026 | C56: Development of machine learning-based multi-task quantitative structure–activity relationship models for predicting toxicities in six human organ systems | D56: Bee toxicity ML | Molecular toxicity ML | E56: Yes | F56: Core | G56: High | H56: Transferable classical molecular toxicity / ecotoxicity ML | I56: DL / neural network | J56: Hepatotoxicity / liver toxicity | K56: Predictive modeling / methodology | L56: 389 chemicals | M56: Molecular descriptors; Molecular graphs | N56: Random Forest; SVM/SVR; Neural network | O56: Cross-validation | P56: Performance was evaluated using nested cross-validation and five metrics (recall, precision, balanced accuracy, F1 score, and ROC-AUC). | Q56: No | R56: Transferable methodology for strengthening classical baselines, representation analysis, validation, interpretability or generalization beyond the base bee-toxicity study. | S56: Computational Toxicology | T56: https://doi.org/10.1016/j.comtox.2025.100399 | U56: https://www.scopus.com/pages/publications/105027095275?origin=resultslist
A57: 56 | B57: 2024 | C57: Toxicology, histophysiological and nutritional changes in Apis mellifera (Hymenoptera: Apidae) submitted to limonene and natural pesticides in comparison to synthetic pesticides | D57: Bee toxicity ML | E57: No | F57: Supporting | G57: Medium | H57: Honey-bee toxicology / problem context | I57: Non-ML / experimental or contextual | J57: Honey-bee / Apis mellifera toxicity | K57: Regression | L57: NR in supplied metadata | M57: NR in supplied metadata | N57: NR in supplied metadata | O57: NR in supplied metadata | P57: NR in supplied abstract | Q57: No | R57: Useful for problem justification, endpoint interpretation, exposure mechanisms, species sensitivity or limitations not captured by structure-only ML. | S57: Journal of Apicultural Research | T57: https://doi.org/10.1080/00218839.2023.2166229 | U57: https://www.scopus.com/pages/publications/85146802245?origin=resultslist
A58: 57 | B58: 2026 | C58: BeeEcoTox: A Large Language Model-Empowered Graph-Learning Framework for Predicting Ecotoxicity of Agrochemicals to Bees | D58: Bee toxicity ML | E58: No | F58: Core | G58: High | H58: Direct honey-bee toxicity ML / QSAR | I58: DL / neural network | J58: Honey-bee / Apis mellifera toxicity | K58: Regression | L58: NR in supplied metadata | M58: Molecular graphs; Molecular graphs / GNN representation | N58: GNN; Neural network | O58: NR in supplied metadata | P58: The rapid and accurate prediction of agrochemical ecotoxicity to bees is thus urgently needed; however, existing models are constrained by single-type structural inputs, resulting in limited accuracy and generalizability. | Q58: No | R58: Direct prior art for the target endpoint; useful for comparing datasets, molecular representations, classical baselines, validation and reported limitations. | S58: Environmental Science and Technology | T58: https://doi.org/10.1021/acs.est.5c18162 | U58: https://www.scopus.com/pages/publications/105036287364?origin=resultslist
A59: 58 | B59: 2023 | C59: Development of a GCN-based model to predict in vitro phototoxicity from the chemical structure and HOMO-LUMO gap | D59: Bee toxicity ML | E59: No | F59: Supporting | G59: Medium | H59: Quantum chemistry + classical ML / molecular modeling | I59: Classical ML with quantum-chemical information | J59: Chemical / molecular toxicity | K59: Predictive modeling / methodology | L59: NR in supplied metadata | M59: Molecular descriptors; HOMO–LUMO descriptors | N59: GCN; CNN; Neural network | O59: NR in supplied metadata | P59: As a result, the assortment of chemical structures and the HOMO-LUMO gap produced an AI model with high discrimination performance, and an F1 score of 0.857. | Q59: Quantum chemistry / QM features; not QML | R59: Useful as adjacent molecular representation work, but quantum-chemical descriptors/calculations are not quantum machine learning. | S59: Journal of Toxicological Sciences | T59: https://doi.org/10.2131/jts.48.243 | U59: https://www.scopus.com/pages/publications/85156255007?origin=resultslist | V59: All Open Access; Gold Open Access
A60: 59 | B60: 2025 | C60: Integrating machine learning and nano-QSAR models to predict the oxidative stress potential caused by single and mixed carbon nanomaterials in algal cells | D60: Bee toxicity ML | E60: No | F60: Exclude | G60: Low | H60: Search noise / outside scope | I60: ML / QSAR | J60: Cytotoxicity | K60: Classification / regression | L60: NR in supplied metadata | M60: Molecular descriptors | N60: Random Forest; Gradient Boosting; SVM/SVR; Neural network; kNN; Logistic Regression | O60: Cross-validation | P60: The Accuracy, Recall, Precision and harmonic mean of Precision and Recall (F1-score) values of these models were all higher than 0.600, indicating an excellent performance in distinguishing whether CNMs have the potential to generate ROS. | Q60: No | R60: Outside the bee-toxicity, transferable molecular-toxicity, or molecular-QML scope of the three searches. | S60: Environmental Toxicology and Chemistry | T60: https://doi.org/10.1093/etojnl/vgae049 | U60: https://www.scopus.com/pages/publications/105014548398?origin=resultslist
A61: 60 | B61: 2026 | C61: An autonomous YOLOv9-edge-to-cloud intelligence system for proactive honeybee mortality mitigation | D61: Bee toxicity ML | E61: No | F61: Core | G61: High | H61: Direct honey-bee toxicity ML / QSAR | I61: DL / neural network | J61: Honey-bee health / toxicity-related outcome | K61: Predictive modeling / methodology | L61: NR in supplied metadata | M61: NR in supplied metadata | N61: ML / QSAR model | O61: NR in supplied metadata | P61: Despite challenges of dense carcass accumulation and occlusion, the system achieved a mean average precision (mAP@0.5) of 0.937. | Q61: No | R61: Direct prior art for the target endpoint; useful for comparing datasets, molecular representations, classical baselines, validation and reported limitations. | S61: Journal of Invertebrate Pathology | T61: https://doi.org/10.1016/j.jip.2026.108691 | U61: https://www.scopus.com/pages/publications/105045268435?origin=resultslist
A62: 61 | B62: 2026 | C62: Malathion impairs sensory perception, learning, and memory, and increases oxidative stress in the western honeybee, Apis mellifera | D62: Bee toxicity ML | E62: No | F62: Supporting | G62: Medium | H62: Honey-bee toxicology / problem context | I62: Non-ML / experimental or contextual | J62: Honey-bee / Apis mellifera toxicity | K62: Regression | L62: NR in supplied metadata | M62: NR in supplied metadata | N62: NR in supplied metadata | O62: NR in supplied metadata | P62: NR in supplied abstract | Q62: No | R62: Useful for problem justification, endpoint interpretation, exposure mechanisms, species sensitivity or limitations not captured by structure-only ML. | S62: Environmental Pollution | T62: https://doi.org/10.1016/j.envpol.2025.127484 | U62: https://www.scopus.com/pages/publications/105024314123?origin=resultslist
A63: 62 | B63: 2025 | C63: Synergistic Effects of Amitraz and Dinotefuran on Honey Bee Health: Impacts on Survival, Gene Expression, and Hypopharyngeal Gland Morphology | D63: Bee toxicity ML | E63: No | F63: Supporting | G63: Medium | H63: Honey-bee toxicology / problem context | I63: Non-ML / experimental or contextual | J63: Honey-bee / Apis mellifera toxicity | K63: Experimental / risk-assessment study | L63: NR in supplied metadata | M63: NR in supplied metadata | N63: NR in supplied metadata | O63: NR in supplied metadata | P63: NR in supplied abstract | Q63: No | R63: Useful for problem justification, endpoint interpretation, exposure mechanisms, species sensitivity or limitations not captured by structure-only ML. | S63: International Journal of Molecular Sciences | T63: https://doi.org/10.3390/ijms26146850 | U63: https://www.scopus.com/pages/publications/105011728170?origin=resultslist | V63: All Open Access; Gold Open Access; Green Open Access
A64: 63 | B64: 2018 | C64: Classification models for identifying substances exhibiting acute contact toxicity in honeybees (Apis mellifera)$ | D64: Bee toxicity ML | E64: No | F64: Core | G64: High | H64: Direct honey-bee toxicity ML / QSAR | I64: ML / QSAR | J64: Honey-bee / Apis mellifera toxicity | K64: Classification / regression | L64: 254 pesticides | M64: Molecular descriptors | N64: Neural network | O64: External validation | P64: NR in supplied abstract | Q64: No | R64: Direct prior art for the target endpoint; useful for comparing datasets, molecular representations, classical baselines, validation and reported limitations. | S64: SAR and QSAR in Environmental Research | T64: https://doi.org/10.1080/1062936X.2018.1513953 | U64: https://www.scopus.com/pages/publications/85053464038?origin=resultslist
A65: 64 | B65: 2024 | C65: A QSAR study for predicting malformation in zebrafish embryo | D65: Bee toxicity ML | E65: No | F65: Exclude | G65: Low | H65: Search noise / outside scope | I65: DL / neural network | J65: Chemical / molecular toxicity | K65: Regression | L65: NR in supplied metadata | M65: Molecular descriptors | N65: Gradient Boosting; Neural network; Logistic Regression | O65: NR in supplied metadata | P65: The models were then validated with test set and various statistical parameters, such as Matthew’s correlation coefficient (MCC) and balanced accuracy (BAC) score, were used to compare the models. | Q65: No | R65: Outside the bee-toxicity, transferable molecular-toxicity, or molecular-QML scope of the three searches. | S65: Toxicology Mechanisms and Methods | T65: https://doi.org/10.1080/15376516.2024.2338907 | U65: https://www.scopus.com/pages/publications/85190993353?origin=resultslist
A66: 65 | B66: 2021 | C66: In Silico Platforms for Predictive Ecotoxicology: From Machine Learning to Deep Learning | D66: Bee toxicity ML | E66: No | F66: Exclude | G66: Low | H66: Search noise / outside scope | I66: DL / neural network | J66: Chemical ecotoxicity | K66: Review / guidance | L66: NR in supplied metadata | M66: NR in supplied metadata | N66: ML / QSAR model | O66: NR in supplied metadata | P66: Such in silico methods have been proven to reduce the duration and cost of environmental toxicity tests, offering high-precision prediction for humans and various ecological species. | Q66: No | R66: Outside the bee-toxicity, transferable molecular-toxicity, or molecular-QML scope of the three searches. | S66: Chemometrics and Cheminformatics in Aquatic Toxicology | T66: https://doi.org/10.1002/9781119681397.ch23 | U66: https://www.scopus.com/pages/publications/85129153257?origin=resultslist
A67: 66 | B67: 2021 | C67: BeeToxAI: An artificial intelligence-based web app to assess acute toxicity of chemicals to honey bees | D67: Bee toxicity ML | E67: No | F67: Core | G67: High | H67: Direct honey-bee toxicity ML / QSAR | I67: ML / QSAR | J67: Honey-bee / Apis mellifera toxicity | K67: Classification / regression | L67: NR in supplied metadata | M67: Molecular fingerprints | N67: Random Forest; Neural network | O67: Applicability-domain analysis | P67: Initially, we developed and externally validated QSAR models for classification (external set accuracy ∼91%) through the combination of Random Forest and molecular fingerprints to predict the potential for chemicals to cause acute contact toxicity and acute oral toxicity to honey bees. | Q67: No | R67: Direct prior art for the target endpoint; useful for comparing datasets, molecular representations, classical baselines, validation and reported limitations. | S67: Artificial Intelligence in the Life Sciences | T67: https://doi.org/10.1016/j.ailsci.2021.100013 | U67: https://www.scopus.com/pages/publications/85132646441?origin=resultslist | V67: All Open Access; Gold Open Access; Green Open Access
A68: 67 | B68: 2015 | C68: Use of artifcial neural networks in the qsar prediction of physicochemical properties and toxicities for reach legislation | D68: Bee toxicity ML | E68: No | F68: Exclude | G68: Low | H68: Search noise / outside scope | I68: ML / QSAR | J68: Mutagenicity / Ames | K68: Regression | L68: NR in supplied metadata | M68: NR in supplied metadata | N68: SVM/SVR; Neural network; Linear Regression | O68: NR in supplied metadata | P68: ANNs generally outperform the main QSAR approach of multiple linear regression (MLR), although other approaches such as support vector machines sometimes outperform ANNs. | Q68: No | R68: Outside the bee-toxicity, transferable molecular-toxicity, or molecular-QML scope of the three searches. | S68: Methods in Molecular Biology | T68: https://doi.org/10.1007/978-1-4939-2239-0_5 | U68: https://www.scopus.com/pages/publications/84917690958?origin=resultslist
A69: 68 | B69: 2026 | C69: AI-powered modeling of bee spermatozoa quality post agrochemical exposure | D69: Bee toxicity ML | E69: No | F69: Core | G69: High | H69: Direct honey-bee toxicity ML / QSAR | I69: ML / QSAR | J69: Honey-bee health / toxicity-related outcome | K69: Classification | L69: NR in supplied metadata | M69: NR in supplied metadata | N69: XGBoost; Gradient Boosting | O69: NR in supplied metadata | P69: K-means clustering identified three distinct spermatozoa quality profiles (low, mid, high), which were validated against reproductive benchmarks and predicted with 96% accuracy using the Extreme Gradient Boosting (XGBoost) algorithm. | Q69: No | R69: Direct prior art for the target endpoint; useful for comparing datasets, molecular representations, classical baselines, validation and reported limitations. | S69: Apidologie | T69: https://doi.org/10.1007/s13592-025-01238-0 | U69: https://www.scopus.com/pages/publications/105027439001?origin=resultslist | V69: All Open Access; Hybrid Gold Open Access
A70: 69 | B70: 2020 | C70: Machine learning and deep learning methods in ecotoxicological QSAR modeling | D70: Bee toxicity ML | Molecular toxicity ML | E70: Yes | F70: Core | G70: High | H70: Transferable classical molecular toxicity / ecotoxicity ML | I70: DL / neural network | J70: Mutagenicity / Ames | K70: Review / guidance | L70: 20,000 molecules | M70: SMILES | N70: CNN; Neural network | O70: NR in supplied metadata | P70: Therefore, prediction is the only available solution, but it poses many challenges in terms of accuracy and interpretability. | Q70: No | R70: Transferable methodology for strengthening classical baselines, representation analysis, validation, interpretability or generalization beyond the base bee-toxicity study. | S70: Methods in Pharmacology and Toxicology | T70: https://doi.org/10.1007/978-1-0716-0150-1_6 | U70: https://www.scopus.com/pages/publications/85078107817?origin=resultslist
A71: 70 | B71: 2022 | C71: Risk assessment of honey bee stressors based on in silico analysis of molecular interactions | D71: Bee toxicity ML | E71: No | F71: Supporting | G71: Medium | H71: Honey-bee toxicology / problem context | I71: Non-ML / experimental or contextual | J71: Honey-bee / Apis mellifera toxicity | K71: Experimental / risk-assessment study | L71: NR in supplied metadata | M71: NR in supplied metadata | N71: NR in supplied metadata | O71: NR in supplied metadata | P71: NR in supplied abstract | Q71: No | R71: Useful for problem justification, endpoint interpretation, exposure mechanisms, species sensitivity or limitations not captured by structure-only ML. | S71: EFSA Journal | T71: https://doi.org/10.2903/j.efsa.2022.e200912 | U71: https://www.scopus.com/pages/publications/85144118989?origin=resultslist | V71: All Open Access; Gold Open Access; Green Open Access
A72: 71 | B72: 2026 | C72: Differential effects of a novel mesoionic insecticide, triflumezopyrim, on Apis mellifera and Apis cerana | D72: Bee toxicity ML | E72: No | F72: Supporting | G72: Medium | H72: Honey-bee toxicology / problem context | I72: Non-ML / experimental or contextual | J72: Honey-bee / Apis mellifera toxicity | K72: Regression | L72: NR in supplied metadata | M72: NR in supplied metadata | N72: NR in supplied metadata | O72: Scaffold-based evaluation | P72: mellifera (17.495 mg/L), indicating approximately 5-fold higher sensitivity to TRF. | Q72: No | R72: Useful for problem justification, endpoint interpretation, exposure mechanisms, species sensitivity or limitations not captured by structure-only ML. | S72: Journal of Hazardous Materials | T72: https://doi.org/10.1016/j.jhazmat.2026.142448 | U72: https://www.scopus.com/pages/publications/105039901881?origin=resultslist
A73: 72 | B73: 2022 | C73: Artificial Intelligence-Aided Meta-Analysis of Toxicological Assessment of Agrochemicals in Bees | D73: Bee toxicity ML | E73: No | F73: Core | G73: High | H73: Direct honey-bee toxicity ML / QSAR | I73: ML / QSAR | J73: Honey-bee / Apis mellifera toxicity | K73: Review / guidance | L73: NR in supplied metadata | M73: NR in supplied metadata | N73: ML / QSAR model | O73: NR in supplied metadata | P73: NR in supplied abstract | Q73: No | R73: Direct prior art for the target endpoint; useful for comparing datasets, molecular representations, classical baselines, validation and reported limitations. | S73: Frontiers in Ecology and Evolution | T73: https://doi.org/10.3389/fevo.2022.845608 | U73: https://www.scopus.com/pages/publications/85131692334?origin=resultslist | V73: All Open Access; Gold Open Access; Green Open Access
A74: 73 | B74: 2014 | C74: QSTR modeling for qualitative and quantitative toxicity predictions of diverse chemical pesticides in honey bee for regulatory purposes | D74: Bee toxicity ML | E74: No | F74: Core | G74: High | H74: Direct honey-bee toxicity ML / QSAR | I74: ML / QSAR | J74: Honey-bee / Apis mellifera toxicity | K74: Classification / regression | L74: NR in supplied metadata | M74: NR in supplied metadata | N74: Random Forest; SVM/SVR; Neural network | O74: NR in supplied metadata | P74: In complete data, the PNN-QSTR model rendered a classification accuracy of 96.62% (two-category) and 95.57% (four-category), while the GRNN-QSTR model yielded a correlation (R2) of 0.841 between the measured and predicted toxicity values with a mean squared error (MSE) of 0.22. | Q74: No | R74: Direct prior art for the target endpoint; useful for comparing datasets, molecular representations, classical baselines, validation and reported limitations. | S74: Chemical Research in Toxicology | T74: https://doi.org/10.1021/tx500100m | U74: https://www.scopus.com/pages/publications/84918493465?origin=resultslist
A75: 74 | B75: 2024 | C75: QSAR Classification Modeling Using Machine Learning with a Consensus-Based Approach for Multivariate Chemical Hazard End Points | D75: Bee toxicity ML | Molecular toxicity ML | E75: Yes | F75: Core | G75: High | H75: Transferable classical molecular toxicity / ecotoxicity ML | I75: ML / QSAR | J75: Chemical / molecular toxicity | K75: Classification | L75: NR in supplied metadata | M75: Morgan fingerprints; MACCS; Molecular fingerprints; Molecular descriptors | N75: Random Forest; XGBoost; Gradient Boosting; SVM/SVR | O75: NR in supplied metadata | P75: The consensus model was developed by selecting the best-performing classifier─Random Forest (RF), eXtreme Gradient Boosting (XGBoost), or Support Vector Machines (SVM)─for each descriptor, optimizing predictive accuracy and robustness across the end points. | Q75: No | R75: Transferable methodology for strengthening classical baselines, representation analysis, validation, interpretability or generalization beyond the base bee-toxicity study. | S75: ACS Omega | T75: https://doi.org/10.1021/acsomega.4c09356 | U75: https://www.scopus.com/pages/publications/85211587432?origin=resultslist | V75: All Open Access; Gold Open Access; Green Open Access
A76: 75 | B76: 2024 | C76: Advancing ecotoxicity assessment: Leveraging pre-trained model for bee toxicity and compound degradability prediction | D76: Bee toxicity ML | E76: No | F76: Core | G76: High | H76: Direct honey-bee toxicity ML / QSAR | I76: DL / neural network | J76: Honey-bee / Apis mellifera toxicity | K76: Classification | L76: NR in supplied metadata | M76: Molecular graphs / GNN representation | N76: SVM/SVR; GNN; Neural network | O76: NR in supplied metadata | P76: Additionally, despite the low similarity between the endogenous hormones in bees and the compounds in our dataset, our model confidently predicts that these hormones are non-toxic to bees, which further strengthens the credibility and accuracy of our model. | Q76: No | R76: Direct prior art for the target endpoint; useful for comparing datasets, molecular representations, classical baselines, validation and reported limitations. | S76: Journal of Hazardous Materials | T76: https://doi.org/10.1016/j.jhazmat.2024.134828 | U76: https://www.scopus.com/pages/publications/85195651895?origin=resultslist
A77: 76 | B77: 2024 | C77: Comparative toxicity of oral exposure to paraquat: Survival rates and gene expression in two honey bees species; Apis mellifera and Apis cerana | D77: Bee toxicity ML | E77: No | F77: Supporting | G77: Medium | H77: Honey-bee toxicology / problem context | I77: Non-ML / experimental or contextual | J77: Honey-bee / Apis mellifera toxicity | K77: Regression | L77: NR in supplied metadata | M77: NR in supplied metadata | N77: NR in supplied metadata | O77: NR in supplied metadata | P77: cerana exhibits greater sensitivity to paraquat compared to A. | Q77: No | R77: Useful for problem justification, endpoint interpretation, exposure mechanisms, species sensitivity or limitations not captured by structure-only ML. | S77: Environmental Pollution | T77: https://doi.org/10.1016/j.envpol.2024.125026 | U77: https://www.scopus.com/pages/publications/85205308828?origin=resultslist
A78: 77 | B78: 2020 | C78: Got to write a classic: classical and perturbation-based qsar methods, machine learning, and the monitoring of nanoparticle ecotoxicity | D78: Bee toxicity ML | E78: No | F78: Exclude | G78: Low | H78: Search noise / outside scope | I78: ML / QSAR | J78: Cytotoxicity | K78: Regression | L78: NR in supplied metadata | M78: NR in supplied metadata | N78: Random Forest; SVM/SVR; Neural network; Linear Regression; Bayesian model | O78: Scaffold-based evaluation | P78: NR in supplied abstract | Q78: No | R78: Outside the bee-toxicity, transferable molecular-toxicity, or molecular-QML scope of the three searches. | S78: Methods in Pharmacology and Toxicology | T78: https://doi.org/10.1007/978-1-0716-0150-1_9 | U78: https://www.scopus.com/pages/publications/85078216534?origin=resultslist
A79: 78 | B79: 2020 | C79: Toxicity assessment for safe-by-design nanomaterials using advanced data analytics | D79: Bee toxicity ML | E79: No | F79: Exclude | G79: Low | H79: Search noise / outside scope | I79: ML / QSAR | J79: Cytotoxicity | K79: Classification | L79: NR in supplied metadata | M79: Molecular descriptors; Molecular graphs | N79: ML / QSAR model | O79: NR in supplied metadata | P79: NR in supplied abstract | Q79: No | R79: Outside the bee-toxicity, transferable molecular-toxicity, or molecular-QML scope of the three searches. | S79: Proceedings of the 29th European Safety and Reliability Conference, ESREL 2019 | T79: https://doi.org/10.3850/978-981-11-2724-30895-cd | U79: https://www.scopus.com/pages/publications/85089177035?origin=resultslist
A80: 79 | B80: 2024 | C80: Artificial intelligence-driven tool for spectral analysis: identifying pesticide contamination in bees from reflectance profiling | D80: Bee toxicity ML | E80: No | F80: Core | G80: High | H80: Direct honey-bee toxicity ML / QSAR | I80: ML / QSAR | J80: Honey-bee / Apis mellifera toxicity | K80: Classification | L80: NR in supplied metadata | M80: NR in supplied metadata | N80: ML / QSAR model | O80: NR in supplied metadata | P80: The best-performing model, the linear discriminant analysis, achieved 98 % accuracy in discriminating contamination across species Apis mellifera, Melipona mondury, and Partamona helleri, with prediction speeds of 0.27 s. | Q80: No | R80: Direct prior art for the target endpoint; useful for comparing datasets, molecular representations, classical baselines, validation and reported limitations. | S80: Journal of Hazardous Materials | T80: https://doi.org/10.1016/j.jhazmat.2024.136425 | U80: https://www.scopus.com/pages/publications/85208767895?origin=resultslist
A81: 80 | B81: 2026 | C81: A harmonized ecotoxicity dataset for honeybee based on the ECOTOX database | D81: Bee toxicity ML | E81: No | F81: Supporting | G81: Medium | H81: Honey-bee toxicology / problem context | I81: Non-ML / experimental or contextual | J81: Honey-bee / Apis mellifera toxicity | K81: Regression | L81: 540 chemicals | M81: NR in supplied metadata | N81: Linear Regression | O81: NR in supplied metadata | P81: Subsequently, weighted linear regressions were applied to extrapolate various endpoints to a harmonized ED10-equivalent (ED10eq), with R2 ranging from 0.38–0.99. | Q81: No | R81: Useful for problem justification, endpoint interpretation, exposure mechanisms, species sensitivity or limitations not captured by structure-only ML. | S81: Environmental Toxicology and Chemistry | T81: https://doi.org/10.1093/etojnl/vgag054 | U81: https://www.scopus.com/pages/publications/105042186818?origin=resultslist | V81: All Open Access; Hybrid Gold Open Access
A82: 81 | B82: 2026 | C82: Interpretable machine learning framework for predicting pesticide phytotoxicity in wastewater reuse: Integrating molecular, quantum, and experimental descriptors | D82: Bee toxicity ML | E82: No | F82: Supporting | G82: Medium | H82: Quantum chemistry + classical ML / molecular modeling | I82: Classical ML with quantum-chemical information | J82: Chemical ecotoxicity | K82: Regression | L82: NR in supplied metadata | M82: Molecular descriptors | N82: XGBoost | O82: External validation; Cross-validation | P82: This integration of intrinsic chemical properties and contextual environmental factors not only enhanced predictive accuracy but also provided crucial model interpretability, moving beyond traditional black-box approaches. | Q82: Quantum chemistry / QM features; not QML | R82: Useful as adjacent molecular representation work, but quantum-chemical descriptors/calculations are not quantum machine learning. | S82: Environmental Research | T82: https://doi.org/10.1016/j.envres.2025.123389 | U82: https://www.scopus.com/pages/publications/105022644568?origin=resultslist
A83: 82 | B83: 2020 | C83: Use of machine learning and classical QSAR methods in computational ecotoxicology | D83: Bee toxicity ML | Molecular toxicity ML | E83: Yes | F83: Exclude | G83: Low | H83: Search noise / outside scope | I83: ML / QSAR | J83: Chemical ecotoxicity | K83: Predictive modeling / methodology | L83: NR in supplied metadata | M83: NR in supplied metadata | N83: ML / QSAR model | O83: NR in supplied metadata | P83: NR in supplied abstract | Q83: No | R83: Outside the bee-toxicity, transferable molecular-toxicity, or molecular-QML scope of the three searches. | S83: Methods in Pharmacology and Toxicology | T83: https://doi.org/10.1007/978-1-0716-0150-1_7 | U83: https://www.scopus.com/pages/publications/85078166227?origin=resultslist
A84: 83 | B84: 2025 | C84: Deep Learning-Driven Discovery of Bee-Safe Isoxazoline Pesticide Candidates | D84: Bee toxicity ML | E84: No | F84: Core | G84: High | H84: Direct honey-bee toxicity ML / QSAR | I84: DL / neural network | J84: Honey-bee / Apis mellifera toxicity | K84: Predictive modeling / methodology | L84: NR in supplied metadata | M84: Molecular graphs / GNN representation | N84: GNN; Neural network | O84: NR in supplied metadata | P84: BeeSafe 2.0 demonstrates superior predictive performance, specifically overcoming previous limitations for isoxazolines, and provides an accessible online server (www.beesafe.top) for chemical bee toxicity assessment. | Q84: No | R84: Direct prior art for the target endpoint; useful for comparing datasets, molecular representations, classical baselines, validation and reported limitations. | S84: Journal of Agricultural and Food Chemistry | T84: https://doi.org/10.1021/acs.jafc.5c12299 | U84: https://www.scopus.com/pages/publications/105024447022?origin=resultslist
A85: 84 | B85: 2022 | C85: Exploring the potential of in silico machine learning tools for the prediction of acute Daphnia magna nanotoxicity | D85: Bee toxicity ML | E85: No | F85: Exclude | G85: Low | H85: Search noise / outside scope | I85: ML / QSAR | J85: Biodegradability | K85: Classification | L85: NR in supplied metadata | M85: Molecular descriptors | N85: Random Forest; Neural network; kNN | O85: NR in supplied metadata | P85: Results indicated highly comparable model performance between all algorithms and predictive performance exceeding ∼0.7 for all evaluated metrics (e.g. | Q85: No | R85: Outside the bee-toxicity, transferable molecular-toxicity, or molecular-QML scope of the three searches. | S85: Chemosphere | T85: https://doi.org/10.1016/j.chemosphere.2022.135930 | U85: https://www.scopus.com/pages/publications/85135935279?origin=resultslist | V85: All Open Access; Green Open Access; Hybrid Gold Open Access
A86: 85 | B86: 2020 | C86: Graph attention convolutional neural network model for chemical poisoning of honey bees’ prediction | D86: Bee toxicity ML | E86: No | F86: Core | G86: High | H86: Direct honey-bee toxicity ML / QSAR | I86: DL / neural network | J86: Honey-bee / Apis mellifera toxicity | K86: Classification | L86: 720 pesticides | M86: NR in supplied metadata | N86: GAT; CNN; Neural network | O86: External validation | P86: The first case represents the accuracy in identifying bee poisonous chemicals. | Q86: No | R86: Direct prior art for the target endpoint; useful for comparing datasets, molecular representations, classical baselines, validation and reported limitations. | S86: Science Bulletin | T86: https://doi.org/10.1016/j.scib.2020.04.006 | U86: https://www.scopus.com/pages/publications/85083577047?origin=resultslist
A87: 86 | B87: 2018 | C87: Toxicity and poisoning symptoms of selected insecticides to honey bees (Apis mellifera mellifera L.) | D87: Bee toxicity ML | E87: No | F87: Supporting | G87: Medium | H87: Honey-bee toxicology / problem context | I87: Non-ML / experimental or contextual | J87: Honey-bee / Apis mellifera toxicity | K87: Regression | L87: NR in supplied metadata | M87: NR in supplied metadata | N87: NR in supplied metadata | O87: NR in supplied metadata | P87: NR in supplied abstract | Q87: No | R87: Useful for problem justification, endpoint interpretation, exposure mechanisms, species sensitivity or limitations not captured by structure-only ML. | S87: Archives of Biological Sciences | T87: https://doi.org/10.2298/ABS170131020P | U87: https://www.scopus.com/pages/publications/85043708912?origin=resultslist | V87: All Open Access; Gold Open Access; Green Open Access
A88: 87 | B88: 2026 | C88: Ionic liquid toxicity prediction and mechanism research based on machine learning and interpretability analysis | D88: Bee toxicity ML | E88: No | F88: Supporting | G88: Medium | H88: Quantum chemistry + classical ML / molecular modeling | I88: Classical ML with quantum-chemical information | J88: Chemical / molecular toxicity | K88: Review / guidance | L88: NR in supplied metadata | M88: Molecular descriptors; SMILES | N88: Random Forest; CNN; Neural network | O88: NR in supplied metadata | P88: fischeri model performing exceptionally well (R2 = 0.9819, MSE = 0.02593). | Q88: Quantum chemistry / QM features; not QML | R88: Useful as adjacent molecular representation work, but quantum-chemical descriptors/calculations are not quantum machine learning. | S88: Chemical Engineering Science | T88: https://doi.org/10.1016/j.ces.2025.122669 | U88: https://www.scopus.com/pages/publications/105017225401?origin=resultslist
A89: 88 | B89: 2024 | C89: Explainable artificial intelligence (XAI) to find optimal in-silico biomarkers for cardiac drug toxicity evaluation | D89: Bee toxicity ML | E89: No | F89: Exclude | G89: Low | H89: Search noise / outside scope | I89: ML / QSAR | J89: Chemical / molecular toxicity | K89: Classification | L89: NR in supplied metadata | M89: NR in supplied metadata | N89: Random Forest; XGBoost; SVM/SVR; Neural network; kNN | O89: NR in supplied metadata | P89: We found that the ANN model coupled with the eleven most influential in-silico biomarkers namely dVmdtrepol,dVmdtmax,APD90,APD50,APDtri,CaD90,CaD50,Catri,CaDiastole,qInward,andqNet showed the highest classification performance among all classifiers with Area Under the Curve (AUC) scores of 0.92 for predicting high-risk, 0.83 for intermediate-risk, | Q89: No | R89: Outside the bee-toxicity, transferable molecular-toxicity, or molecular-QML scope of the three searches. | S89: Scientific Reports | T89: https://doi.org/10.1038/s41598-024-71169-w | U89: https://www.scopus.com/pages/publications/85206279787?origin=resultslist | V89: All Open Access; Gold Open Access; Green Open Access
A90: 89 | B90: 2023 | C90: Guidance for good practice in the application of machine learning in development of toxicological quantitative structure-activity relationships (QSARs) | D90: Bee toxicity ML | E90: No | F90: Exclude | G90: Low | H90: Search noise / outside scope | I90: ML / QSAR | J90: Chemical / molecular toxicity | K90: Review / guidance | L90: NR in supplied metadata | M90: Molecular descriptors | N90: Linear Regression | O90: Cross-validation | P90: NR in supplied abstract | Q90: No | R90: Outside the bee-toxicity, transferable molecular-toxicity, or molecular-QML scope of the three searches. | S90: PLoS ONE | T90: https://doi.org/10.1371/journal.pone.0282924 | U90: https://www.scopus.com/pages/publications/85158860239?origin=resultslist | V90: All Open Access; Gold Open Access; Green Open Access
A91: 90 | B91: 2021 | C91: Apis mellifera and Melipona scutellaris exhibit differential sensitivity to thiamethoxam | D91: Bee toxicity ML | E91: No | F91: Supporting | G91: Medium | H91: Honey-bee toxicology / problem context | I91: Non-ML / experimental or contextual | J91: Honey-bee / Apis mellifera toxicity | K91: Regression | L91: NR in supplied metadata | M91: NR in supplied metadata | N91: NR in supplied metadata | O91: NR in supplied metadata | P91: Thus, the present study quantified the differential sensitivity of the bees M. | Q91: No | R91: Useful for problem justification, endpoint interpretation, exposure mechanisms, species sensitivity or limitations not captured by structure-only ML. | S91: Environmental Pollution | T91: https://doi.org/10.1016/j.envpol.2020.115770 | U91: https://www.scopus.com/pages/publications/85092365396?origin=resultslist | V91: All Open Access; Green Open Access
A92: 91 | B92: 2025 | C92: Towards Rational Pesticide Design with Graph Machine Learning Models for Ecotoxicology | D92: Bee toxicity ML | Molecular toxicity ML | E92: Yes | F92: Core | G92: High | H92: Direct honey-bee toxicity ML / QSAR | I92: DL / neural network | J92: Honey-bee / Apis mellifera toxicity | K92: Classification | L92: ApisTox | M92: Molecular fingerprints; Molecular graphs | N92: Transformer | O92: NR in supplied metadata | P92: NR in supplied abstract | Q92: No | R92: Direct prior art for the target endpoint; useful for comparing datasets, molecular representations, classical baselines, validation and reported limitations. | S92: CIKM 2025 - Proceedings of the 34th ACM International Conference on Information and Knowledge Management | T92: https://doi.org/10.1145/3746252.3761660 | U92: https://www.scopus.com/pages/publications/105023188025?origin=resultslist | V92: All Open Access; Gold Open Access
A93: 92 | B93: 2004 | C93: Three new consensus QSAR models for the prediction of Ames genotoxicity | D93: Molecular toxicity ML | E93: No | F93: Core | G93: High | H93: Transferable classical molecular toxicity / ecotoxicity ML | I93: ML / QSAR | J93: Mutagenicity / Ames | K93: Classification | L93: 400 compounds | M93: Molecular descriptors | N93: Neural network; kNN | O93: External validation | P93: Substantially higher specificity was achieved with these new models as compared with MULTICASE or DEREK with comparable sensitivities among all models. | Q93: No | R93: Transferable methodology for strengthening classical baselines, representation analysis, validation, interpretability or generalization beyond the base bee-toxicity study. | S93: Mutagenesis | T93: https://doi.org/10.1093/mutage/geh043 | U93: https://www.scopus.com/pages/publications/6444224986?origin=resultslist
A94: 93 | B94: 2022 | C94: ADMETboost: a web server for accurate ADMET prediction | D94: Molecular toxicity ML | E94: No | F94: Core | G94: Medium | H94: Transferable classical molecular toxicity / ecotoxicity ML | I94: ML / QSAR | J94: ADME-Tox / ADMET properties | K94: Regression | L94: NR in supplied metadata | M94: Molecular fingerprints; Molecular descriptors | N94: XGBoost; Gradient Boosting; Ensemble | O94: NR in supplied metadata | P94: NR in supplied abstract | Q94: No | R94: Transferable methodology for strengthening classical baselines, representation analysis, validation, interpretability or generalization beyond the base bee-toxicity study. | S94: Journal of Molecular Modeling | T94: https://doi.org/10.1007/s00894-022-05373-8 | U94: https://www.scopus.com/pages/publications/85143122941?origin=resultslist | V94: All Open Access; Green Open Access; Hybrid Gold Open Access
A95: 94 | B95: 2022 | C95: Exploration of chemical space with partial labeled noisy student self-training and self-supervised graph embedding | D95: Molecular toxicity ML | E95: No | F95: Core | G95: Medium | H95: Transferable classical molecular toxicity / ecotoxicity ML | I95: DL / neural network | J95: Chemical / molecular toxicity | K95: Predictive modeling / methodology | L95: Tox21 | M95: Molecular fingerprints; Molecular graphs / GNN representation | N95: GNN; Neural network | O95: NR in supplied metadata | P95: NR in supplied abstract | Q95: No | R95: Transferable methodology for strengthening classical baselines, representation analysis, validation, interpretability or generalization beyond the base bee-toxicity study. | S95: BMC Bioinformatics | T95: https://doi.org/10.1186/s12859-022-04681-3 | U95: https://www.scopus.com/pages/publications/85129403439?origin=resultslist | V95: All Open Access; Gold Open Access; Green Open Access
A96: 95 | B96: 2026 | C96: ADFC-ATP: Attention-Guided Dual-View Fusion and Contrastive Pretraining for Robust Aquatic Toxicity Prediction | D96: Molecular toxicity ML | E96: No | F96: Core | G96: High | H96: Transferable classical molecular toxicity / ecotoxicity ML | I96: DL / neural network | J96: Chemical ecotoxicity | K96: Regression | L96: NR in supplied metadata | M96: Molecular fingerprints; Molecular graphs; Molecular graphs / GNN representation | N96: GNN; GCN; GAT; Neural network | O96: Scaffold-based evaluation | P96: Experimental results show that on four fish toxicity datasets, the AUC of ADFC-ATP achieves an average relative improvement of approximately 10.2% compared to two classic graph neural network baseline models: single-task graph convolutional network (GCN-ST) and multi-task graph convolutional network (GCN-MT). | Q96: No | R96: Transferable methodology for strengthening classical baselines, representation analysis, validation, interpretability or generalization beyond the base bee-toxicity study. | S96: Journal of Cellular and Molecular Medicine | T96: https://doi.org/10.1111/jcmm.71067 | U96: https://www.scopus.com/pages/publications/105031092429?origin=resultslist | V96: All Open Access; Gold Open Access; Green Open Access
A97: 96 | B97: 2018 | C97: Redox biotransformation and delivery of anthracycline anticancer antibiotics: How interpretable structure-activity relationships of lethality using electrophilicity and the london formula for dispersion interaction work | D97: Molecular toxicity ML | E97: No | F97: Core | G97: Medium | H97: Transferable classical molecular toxicity / ecotoxicity ML | I97: Classical ML with quantum-chemical information | J97: Cardiotoxicity | K97: Review / guidance | L97: NR in supplied metadata | M97: Molecular descriptors | N97: ML / QSAR model | O97: Scaffold-based evaluation | P97: Background: Quantum chemical methods and molecular mechanics approaches face a lot of challenges in drug metabolism study because of either insufficient accuracy, huge computational cost, or lack of clear molecular level pictures for building computational models. | Q97: Quantum chemistry / QM features; not QML | R97: Transferable methodology for strengthening classical baselines, representation analysis, validation, interpretability or generalization beyond the base bee-toxicity study. | S97: Current Cancer Drug Targets | T97: https://doi.org/10.2174/1568009617666170330145709 | U97: https://www.scopus.com/pages/publications/85048948626?origin=resultslist
A98: 97 | B98: 2022 | C98: Artificial Intelligence-Based Toxicity Prediction of Environmental Chemicals: Future Directions for Chemical Management Applications | D98: Molecular toxicity ML | E98: No | F98: Core | G98: Medium | H98: Transferable classical molecular toxicity / ecotoxicity ML | I98: DL / neural network | J98: Chemical ecotoxicity | K98: Predictive modeling / methodology | L98: NR in supplied metadata | M98: Molecular fingerprints; Molecular descriptors | N98: Random Forest; Neural network | O98: NR in supplied metadata | P98: NR in supplied abstract | Q98: No | R98: Transferable methodology for strengthening classical baselines, representation analysis, validation, interpretability or generalization beyond the base bee-toxicity study. | S98: Environmental Science and Technology | T98: https://doi.org/10.1021/acs.est.1c07413 | U98: https://www.scopus.com/pages/publications/85133365849?origin=resultslist
A99: 98 | B99: 2005 | C99: Statistically validated QSARs, based on theoretical descriptors, for modeling aquatic toxicity of organic chemicals in Pimephales promelas (fathead minnow) | D99: Molecular toxicity ML | E99: No | F99: Core | G99: High | H99: Transferable classical molecular toxicity / ecotoxicity ML | I99: ML / QSAR | J99: Chemical ecotoxicity | K99: Regression | L99: NR in supplied metadata | M99: Molecular descriptors; 3D molecular information | N99: Neural network; Linear Regression | O99: Cross-validation; Applicability-domain analysis; Bootstrap | P99: NR in supplied abstract | Q99: No | R99: Transferable methodology for strengthening classical baselines, representation analysis, validation, interpretability or generalization beyond the base bee-toxicity study. | S99: Journal of Chemical Information and Modeling | T99: https://doi.org/10.1021/ci0502121 | U99: https://www.scopus.com/pages/publications/26944468691?origin=resultslist
A100: 99 | B100: 2019 | C100: Computational Investigation of Drug Phototoxicity: Photosafety Assessment, Photo-Toxophore Identification, and Machine Learning | D100: Molecular toxicity ML | E100: No | F100: Core | G100: High | H100: Transferable classical molecular toxicity / ecotoxicity ML | I100: Classical ML with quantum-chemical information | J100: Cytotoxicity | K100: Review / guidance | L100: 450 compounds | M100: Molecular fingerprints; Molecular descriptors | N100: Random Forest; Neural network; Bayesian model | O100: NR in supplied metadata | P100: Model accuracies of 83-85% could typically be reached for diverse test data sets and other company in-house data, while model sensitivity (the capability of correctly detecting toxicants) was even better, reaching 86%-90%. | Q100: Quantum chemistry / QM features; not QML | R100: Transferable methodology for strengthening classical baselines, representation analysis, validation, interpretability or generalization beyond the base bee-toxicity study. | S100: Chemical Research in Toxicology | T100: https://doi.org/10.1021/acs.chemrestox.9b00338 | U100: https://www.scopus.com/pages/publications/85074606246?origin=resultslist
...

Sheet Core only
A1: # | B1: Year | C1: Title | D1: Found in search(es) | E1: Duplicate across searches? | F1: Decision | G1: Priority | H1: Relevance category | I1: AI / ML / QML? | J1: What is predicted? | K1: Task | L1: Dataset / N | M1: Input / representation | N1: Models / approach | O1: Validation | P1: Reported result | Q1: Quantum relation | R1: Why useful for our paper? | S1: Source title | T1: DOI | U1: Scopus link | V1: Open access
A2: 1 | B2: 2018 | C2: QSAR modeling in ecotoxicological risk assessment: application to the prediction of acute contact toxicity of pesticides on bees (Apis mellifera L.) | D2: Bee toxicity ML | E2: No | F2: Core | G2: High | H2: Direct honey-bee toxicity ML / QSAR | I2: ML / QSAR | J2: Honey-bee / Apis mellifera toxicity | K2: Classification / regression | L2: 111 pesticides | M2: NR in supplied metadata | N2: ML / QSAR model | O2: External validation | P2: A good correlation between predicted and experimental values was found (R2 = 0.97 and RMSE = 0.14). | Q2: No | R2: Direct prior art for the target endpoint; useful for comparing datasets, molecular representations, classical baselines, validation and reported limitations. | S2: Environmental Science and Pollution Research | T2: https://doi.org/10.1007/s11356-017-0498-9 | U2: https://www.scopus.com/pages/publications/85032016580?origin=resultslist
A3: 2 | B3: 2026 | C3: Meditox: integrating machine learning and molecular data for accurate drug toxicity prediction | D3: Bee toxicity ML | Molecular toxicity ML | E3: Yes | F3: Core | G3: High | H3: Transferable classical molecular toxicity / ecotoxicity ML | I3: DL / neural network | J3: Mutagenicity / Ames | K3: Predictive modeling / methodology | L3: NR in supplied metadata | M3: Molecular fingerprints; Molecular descriptors | N3: ML / QSAR model | O3: External test; Cross-validation | P3: High accuracy and generalizability were validated by external testing and cross-validation. | Q3: No | R3: Transferable methodology for strengthening classical baselines, representation analysis, validation, interpretability or generalization beyond the base bee-toxicity study. | S3: Recent Trends in Data Analytics and Computing: Exploring Emerging Technologies and Future Directions, A proceeding of ICADAC – 2025 | T3: https://doi.org/10.1201/9781003724995-17 | U3: https://www.scopus.com/pages/publications/105027494742?origin=resultslist
A4: 8 | B4: 2026 | C4: BeeMSAI: A multi-dimensional evaluation strategy for honeybee toxicity in agrochemicals integrating mode of action, structural analysis, and AI–powered prediction | D4: Bee toxicity ML | E4: No | F4: Core | G4: High | H4: Direct honey-bee toxicity ML / QSAR | I4: ML / QSAR | J4: Honey-bee / Apis mellifera toxicity | K4: Classification | L4: NR in supplied metadata | M4: NR in supplied metadata | N4: SVM/SVR; GAT; Neural network | O4: NR in supplied metadata | P4: The support vector machine model showed robust predictive performance with an overall accuracy of 81.82 %, with the accuracy for neonicotinoids and new pesticides being 84.21 % and 80.77 %, respectively. | Q4: No | R4: Direct prior art for the target endpoint; useful for comparing datasets, molecular representations, classical baselines, validation and reported limitations. | S4: Journal of Hazardous Materials | T4: https://doi.org/10.1016/j.jhazmat.2025.141018 | U4: https://www.scopus.com/pages/publications/105027181923?origin=resultslist
A5: 10 | B5: 2025 | C5: Developing Computational Toxicology Models to Assess the Risk of Environmental Pollutants on Ecosystem Health | D5: Bee toxicity ML | Molecular toxicity ML | E5: Yes | F5: Core | G5: Medium | H5: Transferable classical molecular toxicity / ecotoxicity ML | I5: ML / QSAR | J5: Chemical / molecular toxicity | K5: Predictive modeling / methodology | L5: NR in supplied metadata | M5: NR in supplied metadata | N5: Random Forest; SVM/SVR; Neural network; kNN | O5: NR in supplied metadata | P5: The models achieved accuracies of 69%, 80%, 71%, and 96% respectively, highlighting the superior performance of the Random Forest approach when compared with other traditional models. | Q5: No | R5: Transferable methodology for strengthening classical baselines, representation analysis, validation, interpretability or generalization beyond the base bee-toxicity study. | S5: INDISCON 2025 - IEEE 6th India Council International Subsections Conference, Proceedings | T5: https://doi.org/10.1109/INDISCON66021.2025.11254833 | U5: https://www.scopus.com/pages/publications/105030159313?origin=resultslist
A6: 11 | B6: 2020 | C6: Predicting the acute ecotoxicity of chemical substances by machine learning using graph theory | D6: Bee toxicity ML | Molecular toxicity ML | E6: Yes | F6: Core | G6: Medium | H6: Transferable classical molecular toxicity / ecotoxicity ML | I6: ML / QSAR | J6: Chemical ecotoxicity | K6: Classification / regression | L6: NR in supplied metadata | M6: MACCS | N6: Linear Regression | O6: NR in supplied metadata | P6: Due to empirical classification, the prediction accuracy does not improve even if new ecotoxicity test data are added. | Q6: No | R6: Transferable methodology for strengthening classical baselines, representation analysis, validation, interpretability or generalization beyond the base bee-toxicity study. | S6: Chemosphere | T6: https://doi.org/10.1016/j.chemosphere.2019.124604 | U6: https://www.scopus.com/pages/publications/85071052153?origin=resultslist
A7: 12 | B7: 2019 | C7: Could deep learning in neural networks improve the QSAR models? | D7: Bee toxicity ML | Molecular toxicity ML | E7: Yes | F7: Core | G7: Medium | H7: Transferable classical molecular toxicity / ecotoxicity ML | I7: DL / neural network | J7: Mutagenicity / Ames | K7: Classification | L7: NR in supplied metadata | M7: Molecular descriptors; Molecular graphs; SMILES | N7: Neural network | O7: NR in supplied metadata | P7: Results of our networks, trained on a ~20K molecule dataset with Ames test experimental values, match or even outperform the current state of the art. | Q7: No | R7: Transferable methodology for strengthening classical baselines, representation analysis, validation, interpretability or generalization beyond the base bee-toxicity study. | S7: SAR and QSAR in Environmental Research | T7: https://doi.org/10.1080/1062936X.2019.1650827 | U7: https://www.scopus.com/pages/publications/85071324022?origin=resultslist
A8: 14 | B8: 2020 | C8: Predicting acute contact toxicity of organic binary mixtures in honey bees (A. mellifera) through innovative QSAR models | D8: Bee toxicity ML | E8: No | F8: Core | G8: High | H8: Direct honey-bee toxicity ML / QSAR | I8: ML / QSAR | J8: Honey-bee pesticide mixture toxicity | K8: Classification / regression | L8: NR in supplied metadata | M8: Molecular graphs; SMILES | N8: ML / QSAR model | O8: NR in supplied metadata | P8: The two regression models were validated for their reliability and robustness (R2 = 0.89, CCC = 0.92, Q2 = 0.81; R2 = 0.87, CCC = 0.89, Q2 = 0.75). | Q8: No | R8: Direct prior art for the target endpoint; useful for comparing datasets, molecular representations, classical baselines, validation and reported limitations. | S8: Science of the Total Environment | T8: https://doi.org/10.1016/j.scitotenv.2019.135302 | U8: https://www.scopus.com/pages/publications/85076609141?origin=resultslist | V8: All Open Access; Bronze Open Access; Green Open Access
A9: 15 | B9: 2024 | C9: Using honey bee flight activity data and a deep learning model as a toxicovigilance tool | D9: Bee toxicity ML | E9: No | F9: Core | G9: High | H9: Direct honey-bee toxicity ML / QSAR | I9: DL / neural network | J9: Honey-bee health / toxicity-related outcome | K9: Classification | L9: NR in supplied metadata | M9: NR in supplied metadata | N9: Neural network | O9: NR in supplied metadata | P9: However, the highest classification accuracy of 99%, a Cohen Kappa of 0.9766, a precision of 0.99, a recall of 0.99, and an F1-score of 0.99 was achieved with the model trained on 25 days of activity data, signifying near-perfect classification ability. | Q9: No | R9: Direct prior art for the target endpoint; useful for comparing datasets, molecular representations, classical baselines, validation and reported limitations. | S9: Ecological Informatics | T9: https://doi.org/10.1016/j.ecoinf.2024.102653 | U9: https://www.scopus.com/pages/publications/85194578152?origin=resultslist | V9: All Open Access; Gold Open Access; Green Open Access
A10: 16 | B10: 2024 | C10: Comprehensive hepatotoxicity prediction: ensemble model integrating machine learning and deep learning | D10: Bee toxicity ML | Molecular toxicity ML | E10: Yes | F10: Core | G10: High | H10: Transferable classical molecular toxicity / ecotoxicity ML | I10: DL / neural network | J10: Hepatotoxicity / liver toxicity | K10: Review / guidance | L10: 2588 chemicals | M10: Molecular fingerprints; Molecular descriptors | N10: Ensemble | O10: External test; Cross-validation | P10: Results: The voting ensemble classifier emerged as the optimal model, achieving an excellent prediction accuracy of 80.26%, AUC of 82.84%, and recall of over 93% followed by bagging and stacking ensemble classifiers method. | Q10: No | R10: Transferable methodology for strengthening classical baselines, representation analysis, validation, interpretability or generalization beyond the base bee-toxicity study. | S10: Frontiers in Pharmacology | T10: https://doi.org/10.3389/fphar.2024.1441587 | U10: https://www.scopus.com/pages/publications/85203458932?origin=resultslist | V10: All Open Access; Gold Open Access; Green Open Access
A11: 17 | B11: 2025 | C11: A Comparative Evaluation of Machine Learning and Deep Graph Learning for Chemical Ecotoxicological Prediction | D11: Bee toxicity ML | Molecular toxicity ML | E11: Yes | F11: Core | G11: Medium | H11: Transferable classical molecular toxicity / ecotoxicity ML | I11: DL / neural network | J11: Chemical ecotoxicity | K11: Predictive modeling / methodology | L11: NR in supplied metadata | M11: Morgan fingerprints; MACCS; Molecular fingerprints; Molecular graphs / GNN representation | N11: GNN; GCN; Neural network | O11: NR in supplied metadata | P11: In the same-species predictions, GCN models achieved the highest values of area under the ROC curve (AUC), ranging between 0.982 and 0.992. | Q11: No | R11: Transferable methodology for strengthening classical baselines, representation analysis, validation, interpretability or generalization beyond the base bee-toxicity study. | S11: ACS Omega | T11: https://doi.org/10.1021/acsomega.5c03753 | U11: https://www.scopus.com/pages/publications/105014545066?origin=resultslist | V11: All Open Access; Gold Open Access; Green Open Access
A12: 18 | B12: 2026 | C12: A QSAR-machine learning hybrid model for predicting the ecotoxicity of soil organic compounds and deriving thresholds | D12: Bee toxicity ML | Molecular toxicity ML | E12: Yes | F12: Core | G12: High | H12: Transferable classical molecular toxicity / ecotoxicity ML | I12: Classical ML with quantum-chemical information | J12: Chemical ecotoxicity | K12: Regression | L12: 305 compounds | M12: Molecular descriptors; Molecular graphs | N12: Random Forest; XGBoost; CatBoost | O12: External validation | P12: The ecological thresholds were derived via species sensitivity distribution (SSD). | Q12: Quantum chemistry / QM features; not QML | R12: Transferable methodology for strengthening classical baselines, representation analysis, validation, interpretability or generalization beyond the base bee-toxicity study. | S12: Journal of Cleaner Production | T12: https://doi.org/10.1016/j.jclepro.2026.147869 | U12: https://www.scopus.com/pages/publications/105030933470?origin=resultslist
A13: 22 | B13: 2026 | C13: Interpretable multi-modality consensus QSAR framework: integrating machine and deep learning for enhanced multi-endpoint toxicity assessment | D13: Bee toxicity ML | Molecular toxicity ML | E13: Yes | F13: Core | G13: High | H13: Transferable classical molecular toxicity / ecotoxicity ML | I13: DL / neural network | J13: Mutagenicity / Ames | K13: Predictive modeling / methodology | L13: 160 compounds | M13: Molecular descriptors | N13: Random Forest; Gradient Boosting; SVM/SVR; Neural network | O13: Cross-validation; Applicability-domain analysis | P13: Models for each descriptor–algorithm combination were optimized using 10-fold cross-validation, and top-performing models were combined into weighted multi-modality consensus predictors based on cross-validated area under the receiver operating characteristic curve (AUC) weights. | Q13: No | R13: Transferable methodology for strengthening classical baselines, representation analysis, validation, interpretability or generalization beyond the base bee-toxicity study. | S13: Toxicology Mechanisms and Methods | T13: https://doi.org/10.1080/15376516.2026.2643659 | U13: https://www.scopus.com/pages/publications/105033707008?origin=resultslist
A14: 24 | B14: 2026 | C14: Evaluating machine learning models for predicting pesticide toxicity to honey bees | D14: Bee toxicity ML | E14: No | F14: Core | G14: High | H14: Direct honey-bee toxicity ML / QSAR | I14: DL / neural network | J14: Honey-bee / Apis mellifera toxicity | K14: Predictive modeling / methodology | L14: ApisTox | M14: Molecular fingerprints; Molecular graphs / GNN representation | N14: GNN; Neural network | O14: Cross-validation | P14: NR in supplied abstract | Q14: No | R14: Direct prior art for the target endpoint; useful for comparing datasets, molecular representations, classical baselines, validation and reported limitations. | S14: Ecotoxicology and Environmental Safety | T14: https://doi.org/10.1016/j.ecoenv.2026.119869 | U14: https://www.scopus.com/pages/publications/105031117980?origin=resultslist | V14: All Open Access; Gold Open Access; Green Open Access
A15: 25 | B15: 2017 | C15: Predicting acute contact toxicity of pesticides in honeybees (Apis mellifera) through a k-nearest neighbor model | D15: Bee toxicity ML | E15: No | F15: Core | G15: High | H15: Direct honey-bee toxicity ML / QSAR | I15: ML / QSAR | J15: Honey-bee / Apis mellifera toxicity | K15: Regression | L15: 256 pesticides | M15: NR in supplied metadata | N15: kNN | O15: NR in supplied metadata | P15: The k-NN models were validated with good prediction, with an accuracy of 70% for all compounds and of 65% for highly toxic compounds, suggesting that they might reliably predict the toxicity of structurally diverse pesticides and could be used to screen and prioritise new pesticides. | Q15: No | R15: Direct prior art for the target endpoint; useful for comparing datasets, molecular representations, classical baselines, validation and reported limitations. | S15: Chemosphere | T15: https://doi.org/10.1016/j.chemosphere.2016.09.092 | U15: https://www.scopus.com/pages/publications/84989287587?origin=resultslist
A16: 26 | B16: 2024 | C16: Leveraging In Silico Structure-Activity Models to Predict Acute Honey Bee (Apis mellifera) Toxicity for Agrochemicals | D16: Bee toxicity ML | E16: No | F16: Core | G16: High | H16: Direct honey-bee toxicity ML / QSAR | I16: ML / QSAR | J16: Honey-bee / Apis mellifera toxicity | K16: Classification | L16: 1542 compounds | M16: NR in supplied metadata | N16: Neural network | O16: NR in supplied metadata | P16: Bee toxicity data from 1542 compounds were used to develop models; the sensitivity and specificity of the best model were 0.90 and 0.91, respectively. | Q16: No | R16: Direct prior art for the target endpoint; useful for comparing datasets, molecular representations, classical baselines, validation and reported limitations. | S16: Journal of Agricultural and Food Chemistry | T16: https://doi.org/10.1021/acs.jafc.4c02518 | U16: https://www.scopus.com/pages/publications/85203802131?origin=resultslist
A17: 28 | B17: 2022 | C17: Classifying the toxicity of pesticides to honey bees via support vector machines with random walk graph kernels | D17: Bee toxicity ML | E17: No | F17: Core | G17: High | H17: Direct honey-bee toxicity ML / QSAR | I17: ML / QSAR | J17: Honey-bee / Apis mellifera toxicity | K17: Classification | L17: 382 molecules | M17: MACCS; Molecular fingerprints; Molecular graphs | N17: SVM/SVR | O17: NR in supplied metadata | P17: The L-RWGK-SVM achieves an accuracy, precision, recall, and F1 score (mean over 2000 runs) of 0.81, 0.68, 0.71, and 0.69, respectively, on the test data set - with L = 4 being the mode optimal walk length. | Q17: No | R17: Direct prior art for the target endpoint; useful for comparing datasets, molecular representations, classical baselines, validation and reported limitations. | S17: Journal of Chemical Physics | T17: https://doi.org/10.1063/5.0090573 | U17: https://www.scopus.com/pages/publications/85135008849?origin=resultslist
A18: 31 | B18: 2025 | C18: Predicting Pesticide LC50 Toxicity Using Convolutional Neural Networks and Dragonfly-Support Vector Machine Methods with Quantitative Structure-Activity Relationship and 2D Molecular Fingerprints: A Case Study on Oncorhynchus Mykiss | D18: Bee toxicity ML | Molecular toxicity ML | E18: Yes | F18: Core | G18: High | H18: Transferable classical molecular toxicity / ecotoxicity ML | I18: DL / neural network | J18: Chemical ecotoxicity | K18: Regression | L18: 200 pesticides | M18: Morgan fingerprints; Molecular fingerprints; Molecular descriptors | N18: SVM/SVR; CNN; Neural network | O18: NR in supplied metadata | P18: Model 3 presents the best performance by achieving high predictive global accuracy in terms of RMSE of 0.1755, R² of 0.9860, AARD of 2.9765% and MAE of 0.0590. | Q18: No | R18: Transferable methodology for strengthening classical baselines, representation analysis, validation, interpretability or generalization beyond the base bee-toxicity study. | S18: Chemistry Africa | T18: https://doi.org/10.1007/s42250-025-01239-7 | U18: https://www.scopus.com/pages/publications/86000347183?origin=resultslist
A19: 35 | B19: 2025 | C19: New generation of QSAR modeling for bee safety: predicting toxicity using graph neural networks and apistox data | D19: Bee toxicity ML | Molecular toxicity ML | E19: Yes | F19: Core | G19: High | H19: Direct honey-bee toxicity ML / QSAR | I19: DL / neural network | J19: Honey-bee / Apis mellifera toxicity | K19: Predictive modeling / methodology | L19: ApisTox | M19: Molecular graphs; Molecular graphs / GNN representation; SMILES | N19: GNN; Neural network | O19: Cross-validation | P19: The model achieved an average AUC-ROC of 0.76 on the test set and 0.97 on the training set, with low standard deviations (± 0.03), indicating consistent performance across cross-validation folds. | Q19: No | R19: Direct prior art for the target endpoint; useful for comparing datasets, molecular representations, classical baselines, validation and reported limitations. | S19: Ecotoxicology | T19: https://doi.org/10.1007/s10646-025-02970-0 | U19: https://www.scopus.com/pages/publications/105016759455?origin=resultslist
A20: 40 | B20: 2023 | C20: Deep learning using molecular image of chemical structure | D20: Bee toxicity ML | Molecular toxicity ML | E20: Yes | F20: Core | G20: High | H20: Transferable classical molecular toxicity / ecotoxicity ML | I20: DL / neural network | J20: Chemical / molecular toxicity | K20: Review / guidance | L20: NR in supplied metadata | M20: Molecular descriptors; Molecular images; 3D molecular information | N20: ML / QSAR model | O20: NR in supplied metadata | P20: NR in supplied abstract | Q20: No | R20: Transferable methodology for strengthening classical baselines, representation analysis, validation, interpretability or generalization beyond the base bee-toxicity study. | S20: Cheminformatics, QSAR and Machine Learning Applications for Novel Drug Development | T20: https://doi.org/10.1016/B978-0-443-18638-7.00005-0 | U20: https://www.scopus.com/pages/publications/85163448577?origin=resultslist
A21: 44 | B21: 2017 | C21: Insights into the Molecular Basis of the Acute Contact Toxicity of Diverse Organic Chemicals in the Honey Bee | D21: Bee toxicity ML | E21: No | F21: Core | G21: High | H21: Direct honey-bee toxicity ML / QSAR | I21: ML / QSAR | J21: Honey-bee / Apis mellifera toxicity | K21: Classification / regression | L21: NR in supplied metadata | M21: Molecular fingerprints; Molecular descriptors | N21: ML / QSAR model | O21: External validation; Cross-validation | P21: NR in supplied abstract | Q21: No | R21: Direct prior art for the target endpoint; useful for comparing datasets, molecular representations, classical baselines, validation and reported limitations. | S21: Journal of Chemical Information and Modeling | T21: https://doi.org/10.1021/acs.jcim.7b00476 | U21: https://www.scopus.com/pages/publications/85039988952?origin=resultslist
A22: 45 | B22: 2026 | C22: Machine learning based assessment of the toxicity of polymeric materials to green algae as an approach to design non-toxic polymeric coatings to deter marine biofouling | D22: Bee toxicity ML | Molecular toxicity ML | E22: Yes | F22: Core | G22: Medium | H22: Transferable classical molecular toxicity / ecotoxicity ML | I22: ML / QSAR | J22: Chemical ecotoxicity | K22: Regression | L22: NR in supplied metadata | M22: Molecular descriptors | N22: ML / QSAR model | O22: NR in supplied metadata | P22: The best models were selected based on their performance on training ( R 2 train , Q 2 , RMSE ) and validation sets ( R 2 test , y -scrambling). | Q22: No | R22: Transferable methodology for strengthening classical baselines, representation analysis, validation, interpretability or generalization beyond the base bee-toxicity study. | S22: Results in Chemistry | T22: https://doi.org/10.1016/j.rechem.2025.103005 | U22: https://www.scopus.com/pages/publications/105026149047?origin=resultslist | V22: All Open Access; Gold Open Access
A23: 46 | B23: 2022 | C23: Chemometric modeling of plant protection products (PPPs) for the prediction of acute contact toxicity against honey bees (A. mellifera): A 2D-QSAR approach | D23: Bee toxicity ML | E23: No | F23: Core | G23: High | H23: Direct honey-bee toxicity ML / QSAR | I23: ML / QSAR | J23: Honey-bee / Apis mellifera toxicity | K23: Regression | L23: 709 compounds | M23: Molecular graphs | N23: ML / QSAR model | O23: External validation; Applicability-domain analysis | P23: The obtained results (R2 = 0.666, Q2 = 0.594, Q2F1 = 0.647 and Q2F2 = 0.646) determine the predictability and reliability of the developed model. | Q23: No | R23: Direct prior art for the target endpoint; useful for comparing datasets, molecular representations, classical baselines, validation and reported limitations. | S23: Journal of Hazardous Materials | T23: https://doi.org/10.1016/j.jhazmat.2021.127230 | U23: https://www.scopus.com/pages/publications/85115387479?origin=resultslist
A24: 48 | B24: 2020 | C24: Integrating QSAR models predicting acute contact toxicity and mode of action profiling in honey bees (A. mellifera): Data curation using open source databases, performance testing and validation | D24: Bee toxicity ML | E24: No | F24: Core | G24: High | H24: Direct honey-bee toxicity ML / QSAR | I24: ML / QSAR | J24: Honey-bee pesticide mixture toxicity | K24: Review / guidance | L24: 113 pesticides | M24: Molecular graphs | N24: ML / QSAR model | O24: NR in supplied metadata | P24: The two-category QSAR model (toxic/non-toxic; n = 411) was validated using sensitivity (=0.93), specificity (=0.85), balanced accuracy (=0.90), and Matthews correlation coefficient (MCC = 0.78) as statistical parameters. | Q24: No | R24: Direct prior art for the target endpoint; useful for comparing datasets, molecular representations, classical baselines, validation and reported limitations. | S24: Science of the Total Environment | T24: https://doi.org/10.1016/j.scitotenv.2020.139243 | U24: https://www.scopus.com/pages/publications/85085321096?origin=resultslist | V24: All Open Access; Green Open Access; Hybrid Gold Open Access
A25: 49 | B25: 2026 | C25: Honey yield prediction and neonicotinoid risk assessment utilizing a machine learning framework in smart agriculture | D25: Bee toxicity ML | E25: No | F25: Core | G25: High | H25: Direct honey-bee toxicity ML / QSAR | I25: ML / QSAR | J25: Honey-bee / Apis mellifera toxicity | K25: Classification | L25: NR in supplied metadata | M25: NR in supplied metadata | N25: SVM/SVR; Ensemble | O25: NR in supplied metadata | P25: Notably, our proposed voting classifier (AgriBuzzEnsemble), which synergistically fuses Support Vector Machine (SVM) and Gaussian Naive Bayes (GNB), surpassed all baseline models, showcasing robust accuracy of 98%, a Matthews Correlation Coefficient (MCC) of 0.9751, a specificity of 0.9917, and an ROC AUC of 0.9985. | Q25: No | R25: Direct prior art for the target endpoint; useful for comparing datasets, molecular representations, classical baselines, validation and reported limitations. | S25: Scientific Reports | T25: https://doi.org/10.1038/s41598-026-44811-y | U25: https://www.scopus.com/pages/publications/105040603650?origin=resultslist | V25: All Open Access; Gold Open Access; Green Open Access
A26: 50 | B26: 2023 | C26: Applying Artificial Neural Networks to Oxidative Stress Biomarkers in Forager Honey Bees (Apis mellifera) for Ecological Assessment | D26: Bee toxicity ML | E26: No | F26: Core | G26: High | H26: Direct honey-bee toxicity ML / QSAR | I26: ML / QSAR | J26: Honey-bee / Apis mellifera toxicity | K26: Predictive modeling / methodology | L26: NR in supplied metadata | M26: NR in supplied metadata | N26: Neural network | O26: NR in supplied metadata | P26: NR in supplied abstract | Q26: No | R26: Direct prior art for the target endpoint; useful for comparing datasets, molecular representations, classical baselines, validation and reported limitations. | S26: Toxics | T26: https://doi.org/10.3390/toxics11080661 | U26: https://www.scopus.com/pages/publications/85169152009?origin=resultslist | V26: All Open Access; Gold Open Access; Green Open Access
A27: 52 | B27: 2021 | C27: In silico prediction of chemical acute contact toxicity on honey bees via machine learning methods | D27: Bee toxicity ML | E27: No | F27: Core | G27: High | H27: Direct honey-bee toxicity ML / QSAR | I27: ML / QSAR | J27: Honey-bee / Apis mellifera toxicity | K27: Classification / regression | L27: NR in supplied metadata | M27: Molecular fingerprints | N27: SVM/SVR; CNN; Neural network | O27: Applicability-domain analysis | P27: NR in supplied abstract | Q27: No | R27: Direct prior art for the target endpoint; useful for comparing datasets, molecular representations, classical baselines, validation and reported limitations. | S27: Toxicology in Vitro | T27: https://doi.org/10.1016/j.tiv.2021.105089 | U27: https://www.scopus.com/pages/publications/85099576224?origin=resultslist
A28: 53 | B28: 2026 | C28: Machine learning modeling of acute inhalation toxicity using an RFA-RFR framework, supported by explainable AI and SALI-based activity cliff analysis | D28: Bee toxicity ML | Molecular toxicity ML | E28: Yes | F28: Core | G28: High | H28: Transferable classical molecular toxicity / ecotoxicity ML | I28: ML / QSAR | J28: Chemical / molecular toxicity | K28: Regression | L28: 552 molecules | M28: Molecular descriptors; 3D molecular information | N28: Random Forest | O28: Cross-validation | P28: Importantly, benchmarking against previous QSAR models for inhalation toxicity shows improved predictive accuracy and broader chemical applicability. | Q28: No | R28: Transferable methodology for strengthening classical baselines, representation analysis, validation, interpretability or generalization beyond the base bee-toxicity study. | S28: Journal of Pharmacological and Toxicological Methods | T28: https://doi.org/10.1016/j.vascn.2026.108426 | U28: https://www.scopus.com/pages/publications/105039775493?origin=resultslist
A29: 55 | B29: 2026 | C29: Development of machine learning-based multi-task quantitative structure–activity relationship models for predicting toxicities in six human organ systems | D29: Bee toxicity ML | Molecular toxicity ML | E29: Yes | F29: Core | G29: High | H29: Transferable classical molecular toxicity / ecotoxicity ML | I29: DL / neural network | J29: Hepatotoxicity / liver toxicity | K29: Predictive modeling / methodology | L29: 389 chemicals | M29: Molecular descriptors; Molecular graphs | N29: Random Forest; SVM/SVR; Neural network | O29: Cross-validation | P29: Performance was evaluated using nested cross-validation and five metrics (recall, precision, balanced accuracy, F1 score, and ROC-AUC). | Q29: No | R29: Transferable methodology for strengthening classical baselines, representation analysis, validation, interpretability or generalization beyond the base bee-toxicity study. | S29: Computational Toxicology | T29: https://doi.org/10.1016/j.comtox.2025.100399 | U29: https://www.scopus.com/pages/publications/105027095275?origin=resultslist
A30: 57 | B30: 2026 | C30: BeeEcoTox: A Large Language Model-Empowered Graph-Learning Framework for Predicting Ecotoxicity of Agrochemicals to Bees | D30: Bee toxicity ML | E30: No | F30: Core | G30: High | H30: Direct honey-bee toxicity ML / QSAR | I30: DL / neural network | J30: Honey-bee / Apis mellifera toxicity | K30: Regression | L30: NR in supplied metadata | M30: Molecular graphs; Molecular graphs / GNN representation | N30: GNN; Neural network | O30: NR in supplied metadata | P30: The rapid and accurate prediction of agrochemical ecotoxicity to bees is thus urgently needed; however, existing models are constrained by single-type structural inputs, resulting in limited accuracy and generalizability. | Q30: No | R30: Direct prior art for the target endpoint; useful for comparing datasets, molecular representations, classical baselines, validation and reported limitations. | S30: Environmental Science and Technology | T30: https://doi.org/10.1021/acs.est.5c18162 | U30: https://www.scopus.com/pages/publications/105036287364?origin=resultslist
A31: 60 | B31: 2026 | C31: An autonomous YOLOv9-edge-to-cloud intelligence system for proactive honeybee mortality mitigation | D31: Bee toxicity ML | E31: No | F31: Core | G31: High | H31: Direct honey-bee toxicity ML / QSAR | I31: DL / neural network | J31: Honey-bee health / toxicity-related outcome | K31: Predictive modeling / methodology | L31: NR in supplied metadata | M31: NR in supplied metadata | N31: ML / QSAR model | O31: NR in supplied metadata | P31: Despite challenges of dense carcass accumulation and occlusion, the system achieved a mean average precision (mAP@0.5) of 0.937. | Q31: No | R31: Direct prior art for the target endpoint; useful for comparing datasets, molecular representations, classical baselines, validation and reported limitations. | S31: Journal of Invertebrate Pathology | T31: https://doi.org/10.1016/j.jip.2026.108691 | U31: https://www.scopus.com/pages/publications/105045268435?origin=resultslist
A32: 63 | B32: 2018 | C32: Classification models for identifying substances exhibiting acute contact toxicity in honeybees (Apis mellifera)$ | D32: Bee toxicity ML | E32: No | F32: Core | G32: High | H32: Direct honey-bee toxicity ML / QSAR | I32: ML / QSAR | J32: Honey-bee / Apis mellifera toxicity | K32: Classification / regression | L32: 254 pesticides | M32: Molecular descriptors | N32: Neural network | O32: External validation | P32: NR in supplied abstract | Q32: No | R32: Direct prior art for the target endpoint; useful for comparing datasets, molecular representations, classical baselines, validation and reported limitations. | S32: SAR and QSAR in Environmental Research | T32: https://doi.org/10.1080/1062936X.2018.1513953 | U32: https://www.scopus.com/pages/publications/85053464038?origin=resultslist
A33: 66 | B33: 2021 | C33: BeeToxAI: An artificial intelligence-based web app to assess acute toxicity of chemicals to honey bees | D33: Bee toxicity ML | E33: No | F33: Core | G33: High | H33: Direct honey-bee toxicity ML / QSAR | I33: ML / QSAR | J33: Honey-bee / Apis mellifera toxicity | K33: Classification / regression | L33: NR in supplied metadata | M33: Molecular fingerprints | N33: Random Forest; Neural network | O33: Applicability-domain analysis | P33: Initially, we developed and externally validated QSAR models for classification (external set accuracy ∼91%) through the combination of Random Forest and molecular fingerprints to predict the potential for chemicals to cause acute contact toxicity and acute oral toxicity to honey bees. | Q33: No | R33: Direct prior art for the target endpoint; useful for comparing datasets, molecular representations, classical baselines, validation and reported limitations. | S33: Artificial Intelligence in the Life Sciences | T33: https://doi.org/10.1016/j.ailsci.2021.100013 | U33: https://www.scopus.com/pages/publications/85132646441?origin=resultslist | V33: All Open Access; Gold Open Access; Green Open Access
A34: 68 | B34: 2026 | C34: AI-powered modeling of bee spermatozoa quality post agrochemical exposure | D34: Bee toxicity ML | E34: No | F34: Core | G34: High | H34: Direct honey-bee toxicity ML / QSAR | I34: ML / QSAR | J34: Honey-bee health / toxicity-related outcome | K34: Classification | L34: NR in supplied metadata | M34: NR in supplied metadata | N34: XGBoost; Gradient Boosting | O34: NR in supplied metadata | P34: K-means clustering identified three distinct spermatozoa quality profiles (low, mid, high), which were validated against reproductive benchmarks and predicted with 96% accuracy using the Extreme Gradient Boosting (XGBoost) algorithm. | Q34: No | R34: Direct prior art for the target endpoint; useful for comparing datasets, molecular representations, classical baselines, validation and reported limitations. | S34: Apidologie | T34: https://doi.org/10.1007/s13592-025-01238-0 | U34: https://www.scopus.com/pages/publications/105027439001?origin=resultslist | V34: All Open Access; Hybrid Gold Open Access
A35: 69 | B35: 2020 | C35: Machine learning and deep learning methods in ecotoxicological QSAR modeling | D35: Bee toxicity ML | Molecular toxicity ML | E35: Yes | F35: Core | G35: High | H35: Transferable classical molecular toxicity / ecotoxicity ML | I35: DL / neural network | J35: Mutagenicity / Ames | K35: Review / guidance | L35: 20,000 molecules | M35: SMILES | N35: CNN; Neural network | O35: NR in supplied metadata | P35: Therefore, prediction is the only available solution, but it poses many challenges in terms of accuracy and interpretability. | Q35: No | R35: Transferable methodology for strengthening classical baselines, representation analysis, validation, interpretability or generalization beyond the base bee-toxicity study. | S35: Methods in Pharmacology and Toxicology | T35: https://doi.org/10.1007/978-1-0716-0150-1_6 | U35: https://www.scopus.com/pages/publications/85078107817?origin=resultslist
A36: 72 | B36: 2022 | C36: Artificial Intelligence-Aided Meta-Analysis of Toxicological Assessment of Agrochemicals in Bees | D36: Bee toxicity ML | E36: No | F36: Core | G36: High | H36: Direct honey-bee toxicity ML / QSAR | I36: ML / QSAR | J36: Honey-bee / Apis mellifera toxicity | K36: Review / guidance | L36: NR in supplied metadata | M36: NR in supplied metadata | N36: ML / QSAR model | O36: NR in supplied metadata | P36: NR in supplied abstract | Q36: No | R36: Direct prior art for the target endpoint; useful for comparing datasets, molecular representations, classical baselines, validation and reported limitations. | S36: Frontiers in Ecology and Evolution | T36: https://doi.org/10.3389/fevo.2022.845608 | U36: https://www.scopus.com/pages/publications/85131692334?origin=resultslist | V36: All Open Access; Gold Open Access; Green Open Access
A37: 73 | B37: 2014 | C37: QSTR modeling for qualitative and quantitative toxicity predictions of diverse chemical pesticides in honey bee for regulatory purposes | D37: Bee toxicity ML | E37: No | F37: Core | G37: High | H37: Direct honey-bee toxicity ML / QSAR | I37: ML / QSAR | J37: Honey-bee / Apis mellifera toxicity | K37: Classification / regression | L37: NR in supplied metadata | M37: NR in supplied metadata | N37: Random Forest; SVM/SVR; Neural network | O37: NR in supplied metadata | P37: In complete data, the PNN-QSTR model rendered a classification accuracy of 96.62% (two-category) and 95.57% (four-category), while the GRNN-QSTR model yielded a correlation (R2) of 0.841 between the measured and predicted toxicity values with a mean squared error (MSE) of 0.22. | Q37: No | R37: Direct prior art for the target endpoint; useful for comparing datasets, molecular representations, classical baselines, validation and reported limitations. | S37: Chemical Research in Toxicology | T37: https://doi.org/10.1021/tx500100m | U37: https://www.scopus.com/pages/publications/84918493465?origin=resultslist
A38: 74 | B38: 2024 | C38: QSAR Classification Modeling Using Machine Learning with a Consensus-Based Approach for Multivariate Chemical Hazard End Points | D38: Bee toxicity ML | Molecular toxicity ML | E38: Yes | F38: Core | G38: High | H38: Transferable classical molecular toxicity / ecotoxicity ML | I38: ML / QSAR | J38: Chemical / molecular toxicity | K38: Classification | L38: NR in supplied metadata | M38: Morgan fingerprints; MACCS; Molecular fingerprints; Molecular descriptors | N38: Random Forest; XGBoost; Gradient Boosting; SVM/SVR | O38: NR in supplied metadata | P38: The consensus model was developed by selecting the best-performing classifier─Random Forest (RF), eXtreme Gradient Boosting (XGBoost), or Support Vector Machines (SVM)─for each descriptor, optimizing predictive accuracy and robustness across the end points. | Q38: No | R38: Transferable methodology for strengthening classical baselines, representation analysis, validation, interpretability or generalization beyond the base bee-toxicity study. | S38: ACS Omega | T38: https://doi.org/10.1021/acsomega.4c09356 | U38: https://www.scopus.com/pages/publications/85211587432?origin=resultslist | V38: All Open Access; Gold Open Access; Green Open Access
A39: 75 | B39: 2024 | C39: Advancing ecotoxicity assessment: Leveraging pre-trained model for bee toxicity and compound degradability prediction | D39: Bee toxicity ML | E39: No | F39: Core | G39: High | H39: Direct honey-bee toxicity ML / QSAR | I39: DL / neural network | J39: Honey-bee / Apis mellifera toxicity | K39: Classification | L39: NR in supplied metadata | M39: Molecular graphs / GNN representation | N39: SVM/SVR; GNN; Neural network | O39: NR in supplied metadata | P39: Additionally, despite the low similarity between the endogenous hormones in bees and the compounds in our dataset, our model confidently predicts that these hormones are non-toxic to bees, which further strengthens the credibility and accuracy of our model. | Q39: No | R39: Direct prior art for the target endpoint; useful for comparing datasets, molecular representations, classical baselines, validation and reported limitations. | S39: Journal of Hazardous Materials | T39: https://doi.org/10.1016/j.jhazmat.2024.134828 | U39: https://www.scopus.com/pages/publications/85195651895?origin=resultslist
A40: 79 | B40: 2024 | C40: Artificial intelligence-driven tool for spectral analysis: identifying pesticide contamination in bees from reflectance profiling | D40: Bee toxicity ML | E40: No | F40: Core | G40: High | H40: Direct honey-bee toxicity ML / QSAR | I40: ML / QSAR | J40: Honey-bee / Apis mellifera toxicity | K40: Classification | L40: NR in supplied metadata | M40: NR in supplied metadata | N40: ML / QSAR model | O40: NR in supplied metadata | P40: The best-performing model, the linear discriminant analysis, achieved 98 % accuracy in discriminating contamination across species Apis mellifera, Melipona mondury, and Partamona helleri, with prediction speeds of 0.27 s. | Q40: No | R40: Direct prior art for the target endpoint; useful for comparing datasets, molecular representations, classical baselines, validation and reported limitations. | S40: Journal of Hazardous Materials | T40: https://doi.org/10.1016/j.jhazmat.2024.136425 | U40: https://www.scopus.com/pages/publications/85208767895?origin=resultslist
A41: 83 | B41: 2025 | C41: Deep Learning-Driven Discovery of Bee-Safe Isoxazoline Pesticide Candidates | D41: Bee toxicity ML | E41: No | F41: Core | G41: High | H41: Direct honey-bee toxicity ML / QSAR | I41: DL / neural network | J41: Honey-bee / Apis mellifera toxicity | K41: Predictive modeling / methodology | L41: NR in supplied metadata | M41: Molecular graphs / GNN representation | N41: GNN; Neural network | O41: NR in supplied metadata | P41: BeeSafe 2.0 demonstrates superior predictive performance, specifically overcoming previous limitations for isoxazolines, and provides an accessible online server (www.beesafe.top) for chemical bee toxicity assessment. | Q41: No | R41: Direct prior art for the target endpoint; useful for comparing datasets, molecular representations, classical baselines, validation and reported limitations. | S41: Journal of Agricultural and Food Chemistry | T41: https://doi.org/10.1021/acs.jafc.5c12299 | U41: https://www.scopus.com/pages/publications/105024447022?origin=resultslist
A42: 85 | B42: 2020 | C42: Graph attention convolutional neural network model for chemical poisoning of honey bees’ prediction | D42: Bee toxicity ML | E42: No | F42: Core | G42: High | H42: Direct honey-bee toxicity ML / QSAR | I42: DL / neural network | J42: Honey-bee / Apis mellifera toxicity | K42: Classification | L42: 720 pesticides | M42: NR in supplied metadata | N42: GAT; CNN; Neural network | O42: External validation | P42: The first case represents the accuracy in identifying bee poisonous chemicals. | Q42: No | R42: Direct prior art for the target endpoint; useful for comparing datasets, molecular representations, classical baselines, validation and reported limitations. | S42: Science Bulletin | T42: https://doi.org/10.1016/j.scib.2020.04.006 | U42: https://www.scopus.com/pages/publications/85083577047?origin=resultslist
A43: 91 | B43: 2025 | C43: Towards Rational Pesticide Design with Graph Machine Learning Models for Ecotoxicology | D43: Bee toxicity ML | Molecular toxicity ML | E43: Yes | F43: Core | G43: High | H43: Direct honey-bee toxicity ML / QSAR | I43: DL / neural network | J43: Honey-bee / Apis mellifera toxicity | K43: Classification | L43: ApisTox | M43: Molecular fingerprints; Molecular graphs | N43: Transformer | O43: NR in supplied metadata | P43: NR in supplied abstract | Q43: No | R43: Direct prior art for the target endpoint; useful for comparing datasets, molecular representations, classical baselines, validation and reported limitations. | S43: CIKM 2025 - Proceedings of the 34th ACM International Conference on Information and Knowledge Management | T43: https://doi.org/10.1145/3746252.3761660 | U43: https://www.scopus.com/pages/publications/105023188025?origin=resultslist | V43: All Open Access; Gold Open Access
A44: 92 | B44: 2004 | C44: Three new consensus QSAR models for the prediction of Ames genotoxicity | D44: Molecular toxicity ML | E44: No | F44: Core | G44: High | H44: Transferable classical molecular toxicity / ecotoxicity ML | I44: ML / QSAR | J44: Mutagenicity / Ames | K44: Classification | L44: 400 compounds | M44: Molecular descriptors | N44: Neural network; kNN | O44: External validation | P44: Substantially higher specificity was achieved with these new models as compared with MULTICASE or DEREK with comparable sensitivities among all models. | Q44: No | R44: Transferable methodology for strengthening classical baselines, representation analysis, validation, interpretability or generalization beyond the base bee-toxicity study. | S44: Mutagenesis | T44: https://doi.org/10.1093/mutage/geh043 | U44: https://www.scopus.com/pages/publications/6444224986?origin=resultslist
A45: 93 | B45: 2022 | C45: ADMETboost: a web server for accurate ADMET prediction | D45: Molecular toxicity ML | E45: No | F45: Core | G45: Medium | H45: Transferable classical molecular toxicity / ecotoxicity ML | I45: ML / QSAR | J45: ADME-Tox / ADMET properties | K45: Regression | L45: NR in supplied metadata | M45: Molecular fingerprints; Molecular descriptors | N45: XGBoost; Gradient Boosting; Ensemble | O45: NR in supplied metadata | P45: NR in supplied abstract | Q45: No | R45: Transferable methodology for strengthening classical baselines, representation analysis, validation, interpretability or generalization beyond the base bee-toxicity study. | S45: Journal of Molecular Modeling | T45: https://doi.org/10.1007/s00894-022-05373-8 | U45: https://www.scopus.com/pages/publications/85143122941?origin=resultslist | V45: All Open Access; Green Open Access; Hybrid Gold Open Access
A46: 94 | B46: 2022 | C46: Exploration of chemical space with partial labeled noisy student self-training and self-supervised graph embedding | D46: Molecular toxicity ML | E46: No | F46: Core | G46: Medium | H46: Transferable classical molecular toxicity / ecotoxicity ML | I46: DL / neural network | J46: Chemical / molecular toxicity | K46: Predictive modeling / methodology | L46: Tox21 | M46: Molecular fingerprints; Molecular graphs / GNN representation | N46: GNN; Neural network | O46: NR in supplied metadata | P46: NR in supplied abstract | Q46: No | R46: Transferable methodology for strengthening classical baselines, representation analysis, validation, interpretability or generalization beyond the base bee-toxicity study. | S46: BMC Bioinformatics | T46: https://doi.org/10.1186/s12859-022-04681-3 | U46: https://www.scopus.com/pages/publications/85129403439?origin=resultslist | V46: All Open Access; Gold Open Access; Green Open Access
A47: 95 | B47: 2026 | C47: ADFC-ATP: Attention-Guided Dual-View Fusion and Contrastive Pretraining for Robust Aquatic Toxicity Prediction | D47: Molecular toxicity ML | E47: No | F47: Core | G47: High | H47: Transferable classical molecular toxicity / ecotoxicity ML | I47: DL / neural network | J47: Chemical ecotoxicity | K47: Regression | L47: NR in supplied metadata | M47: Molecular fingerprints; Molecular graphs; Molecular graphs / GNN representation | N47: GNN; GCN; GAT; Neural network | O47: Scaffold-based evaluation | P47: Experimental results show that on four fish toxicity datasets, the AUC of ADFC-ATP achieves an average relative improvement of approximately 10.2% compared to two classic graph neural network baseline models: single-task graph convolutional network (GCN-ST) and multi-task graph convolutional network (GCN-MT). | Q47: No | R47: Transferable methodology for strengthening classical baselines, representation analysis, validation, interpretability or generalization beyond the base bee-toxicity study. | S47: Journal of Cellular and Molecular Medicine | T47: https://doi.org/10.1111/jcmm.71067 | U47: https://www.scopus.com/pages/publications/105031092429?origin=resultslist | V47: All Open Access; Gold Open Access; Green Open Access
A48: 96 | B48: 2018 | C48: Redox biotransformation and delivery of anthracycline anticancer antibiotics: How interpretable structure-activity relationships of lethality using electrophilicity and the london formula for dispersion interaction work | D48: Molecular toxicity ML | E48: No | F48: Core | G48: Medium | H48: Transferable classical molecular toxicity / ecotoxicity ML | I48: Classical ML with quantum-chemical information | J48: Cardiotoxicity | K48: Review / guidance | L48: NR in supplied metadata | M48: Molecular descriptors | N48: ML / QSAR model | O48: Scaffold-based evaluation | P48: Background: Quantum chemical methods and molecular mechanics approaches face a lot of challenges in drug metabolism study because of either insufficient accuracy, huge computational cost, or lack of clear molecular level pictures for building computational models. | Q48: Quantum chemistry / QM features; not QML | R48: Transferable methodology for strengthening classical baselines, representation analysis, validation, interpretability or generalization beyond the base bee-toxicity study. | S48: Current Cancer Drug Targets | T48: https://doi.org/10.2174/1568009617666170330145709 | U48: https://www.scopus.com/pages/publications/85048948626?origin=resultslist
A49: 97 | B49: 2022 | C49: Artificial Intelligence-Based Toxicity Prediction of Environmental Chemicals: Future Directions for Chemical Management Applications | D49: Molecular toxicity ML | E49: No | F49: Core | G49: Medium | H49: Transferable classical molecular toxicity / ecotoxicity ML | I49: DL / neural network | J49: Chemical ecotoxicity | K49: Predictive modeling / methodology | L49: NR in supplied metadata | M49: Molecular fingerprints; Molecular descriptors | N49: Random Forest; Neural network | O49: NR in supplied metadata | P49: NR in supplied abstract | Q49: No | R49: Transferable methodology for strengthening classical baselines, representation analysis, validation, interpretability or generalization beyond the base bee-toxicity study. | S49: Environmental Science and Technology | T49: https://doi.org/10.1021/acs.est.1c07413 | U49: https://www.scopus.com/pages/publications/85133365849?origin=resultslist
A50: 98 | B50: 2005 | C50: Statistically validated QSARs, based on theoretical descriptors, for modeling aquatic toxicity of organic chemicals in Pimephales promelas (fathead minnow) | D50: Molecular toxicity ML | E50: No | F50: Core | G50: High | H50: Transferable classical molecular toxicity / ecotoxicity ML | I50: ML / QSAR | J50: Chemical ecotoxicity | K50: Regression | L50: NR in supplied metadata | M50: Molecular descriptors; 3D molecular information | N50: Neural network; Linear Regression | O50: Cross-validation; Applicability-domain analysis; Bootstrap | P50: NR in supplied abstract | Q50: No | R50: Transferable methodology for strengthening classical baselines, representation analysis, validation, interpretability or generalization beyond the base bee-toxicity study. | S50: Journal of Chemical Information and Modeling | T50: https://doi.org/10.1021/ci0502121 | U50: https://www.scopus.com/pages/publications/26944468691?origin=resultslist
A51: 99 | B51: 2019 | C51: Computational Investigation of Drug Phototoxicity: Photosafety Assessment, Photo-Toxophore Identification, and Machine Learning | D51: Molecular toxicity ML | E51: No | F51: Core | G51: High | H51: Transferable classical molecular toxicity / ecotoxicity ML | I51: Classical ML with quantum-chemical information | J51: Cytotoxicity | K51: Review / guidance | L51: 450 compounds | M51: Molecular fingerprints; Molecular descriptors | N51: Random Forest; Neural network; Bayesian model | O51: NR in supplied metadata | P51: Model accuracies of 83-85% could typically be reached for diverse test data sets and other company in-house data, while model sensitivity (the capability of correctly detecting toxicants) was even better, reaching 86%-90%. | Q51: Quantum chemistry / QM features; not QML | R51: Transferable methodology for strengthening classical baselines, representation analysis, validation, interpretability or generalization beyond the base bee-toxicity study. | S51: Chemical Research in Toxicology | T51: https://doi.org/10.1021/acs.chemrestox.9b00338 | U51: https://www.scopus.com/pages/publications/85074606246?origin=resultslist
A52: 101 | B52: 2026 | C52: Explainable machine learning for predicting PFAS toxicity using molecular descriptors | D52: Molecular toxicity ML | E52: No | F52: Core | G52: High | H52: Transferable classical molecular toxicity / ecotoxicity ML | I52: ML / QSAR | J52: Chemical / molecular toxicity | K52: Predictive modeling / methodology | L52: NR in supplied metadata | M52: Molecular descriptors; SMILES | N52: XGBoost; Gradient Boosting; SVM/SVR; Neural network | O52: NR in supplied metadata | P52: Four ML algorithms, extreme gradient boosting machine (XGBoost), support vector machine (SVM), deep neural networks (DNN), and decision tree (DT), were evaluated, yielding AUROC values of 0.810, 0.817, 0.792, and 0.743, respectively, and average precision values of 0.610, 0.660, 0.584, and 0.443. | Q52: No | R52: Transferable methodology for strengthening classical baselines, representation analysis, validation, interpretability or generalization beyond the base bee-toxicity study. | S52: Environmental Engineering Research | T52: https://doi.org/10.4491/eer.2025.595 | U52: https://www.scopus.com/pages/publications/105029775951?origin=resultslist | V52: All Open Access; Gold Open Access
A53: 102 | B53: 2025 | C53: PHYSPROPNET: A Benchmarking Study of Machine Learning Models for Physicochemical Property Prediction in Data-Limited Environmental Research | D53: Molecular toxicity ML | E53: No | F53: Core | G53: Medium | H53: Transferable classical molecular toxicity / ecotoxicity ML | I53: DL / neural network | J53: Molecular property prediction | K53: Review / guidance | L53: 10,652 compounds | M53: Molecular fingerprints; Molecular descriptors; Molecular graphs / GNN representation | N53: Random Forest; LightGBM; CatBoost; GNN; Neural network | O53: Scaffold-based evaluation | P53: Model accuracy depended primarily on data set size and molecular representation. | Q53: No | R53: Transferable methodology for strengthening classical baselines, representation analysis, validation, interpretability or generalization beyond the base bee-toxicity study. | S53: ACS ES and T Water | T53: https://doi.org/10.1021/acsestwater.5c00850 | U53: https://www.scopus.com/pages/publications/105024705909?origin=resultslist
A54: 103 | B54: 2019 | C54: Consensus QSAR modeling of toxicity of pharmaceuticals to different aquatic organisms: Ranking and prioritization of the DrugBank database compounds | D54: Molecular toxicity ML | E54: No | F54: Core | G54: High | H54: Transferable classical molecular toxicity / ecotoxicity ML | I54: ML / QSAR | J54: Chemical ecotoxicity | K54: Regression | L54: DrugBank | M54: Molecular descriptors | N54: ML / QSAR model | O54: External validation; Cross-validation; Applicability-domain analysis | P54: NR in supplied abstract | Q54: No | R54: Transferable methodology for strengthening classical baselines, representation analysis, validation, interpretability or generalization beyond the base bee-toxicity study. | S54: Ecotoxicology and Environmental Safety | T54: https://doi.org/10.1016/j.ecoenv.2018.10.060 | U54: https://www.scopus.com/pages/publications/85055747171?origin=resultslist
A55: 104 | B55: 2026 | C55: Safe-by-redesign guidance for toxic industrial chemicals using explainable artificial intelligence: Introducing the DETOX-QSAR model | D55: Molecular toxicity ML | E55: No | F55: Core | G55: High | H55: Transferable classical molecular toxicity / ecotoxicity ML | I55: ML / QSAR | J55: Chemical / molecular toxicity | K55: Review / guidance | L55: NR in supplied metadata | M55: Molecular descriptors | N55: Random Forest; XGBoost; CatBoost; Gradient Boosting; SVM/SVR | O55: NR in supplied metadata | P55: NR in supplied abstract | Q55: No | R55: Transferable methodology for strengthening classical baselines, representation analysis, validation, interpretability or generalization beyond the base bee-toxicity study. | S55: Scientific Reports | T55: https://doi.org/10.1038/s41598-026-48176-0 | U55: https://www.scopus.com/pages/publications/105041459466?origin=resultslist | V55: All Open Access; Gold Open Access; Green Open Access
A56: 105 | B56: 2011 | C56: Predicting drug-induced hepatotoxicity using QSAR and toxicogenomics approaches | D56: Molecular toxicity ML | E56: No | F56: Core | G56: Medium | H56: Transferable classical molecular toxicity / ecotoxicity ML | I56: ML / QSAR | J56: Hepatotoxicity / liver toxicity | K56: Classification | L56: NR in supplied metadata | M56: Molecular descriptors; Toxicogenomics | N56: Random Forest; SVM/SVR | O56: Cross-validation | P56: Although the accuracy of hybrid models did not exceed that of the models based on toxicogenomics data alone, the use of both chemical and biological descriptors enriched the interpretation of the models. | Q56: No | R56: Transferable methodology for strengthening classical baselines, representation analysis, validation, interpretability or generalization beyond the base bee-toxicity study. | S56: Chemical Research in Toxicology | T56: https://doi.org/10.1021/tx200148a | U56: https://www.scopus.com/pages/publications/80051727852?origin=resultslist | V56: All Open Access; Green Open Access
A57: 106 | B57: 2023 | C57: MolFPG: Multi-level fingerprint-based Graph Transformer for accurate and robust drug toxicity prediction | D57: Molecular toxicity ML | E57: No | F57: Core | G57: High | H57: Transferable classical molecular toxicity / ecotoxicity ML | I57: DL / neural network | J57: Mutagenicity / Ames | K57: Regression | L57: NR in supplied metadata | M57: Molecular fingerprints | N57: Transformer | O57: NR in supplied metadata | P57: Experimental results show that our proposed approach has high accuracy and reliability in predicting drug toxicity. | Q57: No | R57: Transferable methodology for strengthening classical baselines, representation analysis, validation, interpretability or generalization beyond the base bee-toxicity study. | S57: Computers in Biology and Medicine | T57: https://doi.org/10.1016/j.compbiomed.2023.106904 | U57: https://www.scopus.com/pages/publications/85164302630?origin=resultslist
A58: 107 | B58: 2026 | C58: Multigenerational Toxicity Prediction Using Graph Neural Networks and Biotransformation Analysis | D58: Molecular toxicity ML | E58: No | F58: Core | G58: Medium | H58: Transferable classical molecular toxicity / ecotoxicity ML | I58: DL / neural network | J58: Chemical / molecular toxicity | K58: Regression | L58: NR in supplied metadata | M58: Molecular descriptors; Molecular graphs / GNN representation | N58: XGBoost; GNN; Neural network | O58: NR in supplied metadata | P58: An XGBoost model using PaDEL descriptors achieved high accuracy (R2 = 0.969), while a newly developed Graph Sequence Attention Network (GSAT) yielded comparable results (R2 = 0.907, mean absolute error (MAE) ≈ 0.30) with a 98.9% reduction in computation time, enabling high-throughput screening and substructure-level interpretation. | Q58: No | R58: Transferable methodology for strengthening classical baselines, representation analysis, validation, interpretability or generalization beyond the base bee-toxicity study. | S58: ACS ES and T Water | T58: https://doi.org/10.1021/acsestwater.5c00828 | U58: https://www.scopus.com/pages/publications/105030100970?origin=resultslist
A59: 108 | B59: 2023 | C59: QSAR modeling based on graph neural networks | D59: Molecular toxicity ML | E59: No | F59: Core | G59: High | H59: Transferable classical molecular toxicity / ecotoxicity ML | I59: DL / neural network | J59: Chemical / molecular toxicity | K59: Predictive modeling / methodology | L59: NR in supplied metadata | M59: Molecular graphs / GNN representation | N59: GNN; GAT; Neural network | O59: Applicability-domain analysis | P59: NR in supplied abstract | Q59: No | R59: Transferable methodology for strengthening classical baselines, representation analysis, validation, interpretability or generalization beyond the base bee-toxicity study. | S59: QSAR in Safety Evaluation and Risk Assessment | T59: https://doi.org/10.1016/B978-0-443-15339-6.00012-6 | U59: https://www.scopus.com/pages/publications/85176834143?origin=resultslist
A60: 109 | B60: 2025 | C60: Impact of halogenation on scaffold toxicity assessed using HD-GEM machine learning model | D60: Molecular toxicity ML | E60: No | F60: Core | G60: Medium | H60: Transferable classical molecular toxicity / ecotoxicity ML | I60: DL / neural network | J60: ADME-Tox / ADMET properties | K60: Predictive modeling / methodology | L60: NR in supplied metadata | M60: Molecular fingerprints; Molecular descriptors; Molecular graphs / GNN representation | N60: GNN; Neural network; Ensemble | O60: Scaffold-based evaluation | P60: HD-GEM demonstrates superior predictive power compared to conventional machine learning (ML) models and popular toxicity web applications like ProTox, ADMETlab, and admetSAR, achieving high accuracy and Receiver Operating Characteristic - Area Under Curve scores across diverse datasets. | Q60: No | R60: Transferable methodology for strengthening classical baselines, representation analysis, validation, interpretability or generalization beyond the base bee-toxicity study. | S60: Briefings in Bioinformatics | T60: https://doi.org/10.1093/bib/bbaf347 | U60: https://www.scopus.com/pages/publications/105011167322?origin=resultslist | V60: All Open Access; Gold Open Access; Green Open Access
A61: 110 | B61: 2024 | C61: AI-enhanced chemical paradigm: From molecular graphs to accurate prediction and mechanism | D61: Molecular toxicity ML | E61: No | F61: Core | G61: High | H61: Transferable classical molecular toxicity / ecotoxicity ML | I61: DL / neural network | J61: Other / broad predictive task | K61: Review / guidance | L61: NR in supplied metadata | M61: Molecular fingerprints; Molecular descriptors; Molecular graphs; Molecular graphs / GNN representation | N61: GNN; CNN; Neural network; Bayesian model | O61: Cross-validation; Applicability-domain analysis | P61: NR in supplied abstract | Q61: No | R61: Transferable methodology for strengthening classical baselines, representation analysis, validation, interpretability or generalization beyond the base bee-toxicity study. | S61: Journal of Hazardous Materials | T61: https://doi.org/10.1016/j.jhazmat.2023.133355 | U61: https://www.scopus.com/pages/publications/85181933342?origin=resultslist
A62: 111 | B62: 2023 | C62: QSAR assessment of aquatic toxicity potential of diverse agrochemicals | D62: Molecular toxicity ML | E62: No | F62: Core | G62: Medium | H62: Transferable classical molecular toxicity / ecotoxicity ML | I62: ML / QSAR | J62: Chemical ecotoxicity | K62: Predictive modeling / methodology | L62: NR in supplied metadata | M62: Molecular descriptors; Molecular graphs | N62: ML / QSAR model | O62: NR in supplied metadata | P62: NR in supplied abstract | Q62: No | R62: Transferable methodology for strengthening classical baselines, representation analysis, validation, interpretability or generalization beyond the base bee-toxicity study. | S62: SAR and QSAR in Environmental Research | T62: https://doi.org/10.1080/1062936X.2023.2278074 | U62: https://www.scopus.com/pages/publications/85176323377?origin=resultslist
A63: 112 | B63: 2026 | C63: AMPred-MFG: Investigating the Mutagenicity of Compounds Using Motif-Based Graph Combined with Molecular Fingerprints and Graph Attention Mechanism | D63: Molecular toxicity ML | E63: No | F63: Core | G63: High | H63: Transferable classical molecular toxicity / ecotoxicity ML | I63: DL / neural network | J63: Mutagenicity / Ames | K63: Predictive modeling / methodology | L63: NR in supplied metadata | M63: Molecular fingerprints; Molecular graphs | N63: GAT; Transformer | O63: External validation; Cross-validation | P63: By comparing with several state-of-the-art algorithms, AMPred-MFG achieves the best results in terms of performance, with AUC value of 0.912, ACC of 0.835, SEN of 0.849, NPV of 0.811, PPV of 0.854, MCC of 0.665. | Q63: No | R63: Transferable methodology for strengthening classical baselines, representation analysis, validation, interpretability or generalization beyond the base bee-toxicity study. | S63: Interdisciplinary Sciences - Computational Life Sciences | T63: https://doi.org/10.1007/s12539-025-00742-2 | U63: https://www.scopus.com/pages/publications/105010752253?origin=resultslist
A64: 113 | B64: 2026 | C64: The Tsetlin Machine: A “Third Way” in QSAR Modeling | D64: Molecular toxicity ML | E64: No | F64: Core | G64: High | H64: Transferable classical molecular toxicity / ecotoxicity ML | I64: DL / neural network | J64: Other / broad predictive task | K64: Classification | L64: NR in supplied metadata | M64: ECFP; Molecular fingerprints; Molecular descriptors; Molecular graphs; SMILES | N64: XGBoost; Neural network; Tsetlin Machine | O64: Scaffold-based evaluation | P64: Here we present the Tsetlin Machine (TM)─which combines the accuracy and easy-use of existing rule-based QSAR ML methods (e.g., RF and XGBoost), the iterative learning aspect of NN algorithms and its intrinsic interpretability. | Q64: No | R64: Transferable methodology for strengthening classical baselines, representation analysis, validation, interpretability or generalization beyond the base bee-toxicity study. | S64: Journal of Chemical Information and Modeling | T64: https://doi.org/10.1021/acs.jcim.5c03109 | U64: https://www.scopus.com/pages/publications/105040986445?origin=resultslist | V64: All Open Access; Green Open Access; Hybrid Gold Open Access
A65: 115 | B65: 2026 | C65: Graph neural network-based prediction and interpretation of Daphnia toxicity using distinct scale molecular representations | D65: Molecular toxicity ML | E65: No | F65: Core | G65: High | H65: Transferable classical molecular toxicity / ecotoxicity ML | I65: DL / neural network | J65: Chemical ecotoxicity | K65: Regression | L65: NR in supplied metadata | M65: Molecular graphs; Molecular graphs / GNN representation; SMILES | N65: GNN; CNN; Neural network | O65: NR in supplied metadata | P65: Consequently, the framework using SMARTS-based fragment graph representations consistently achieved a coefficient of determination (R²) above 0.825 regardless of the deep learning architectures, establishing it as the most appropriate representation method. | Q65: No | R65: Transferable methodology for strengthening classical baselines, representation analysis, validation, interpretability or generalization beyond the base bee-toxicity study. | S65: Water Research | T65: https://doi.org/10.1016/j.watres.2026.125676 | U65: https://www.scopus.com/pages/publications/105032084109?origin=resultslist
A66: 116 | B66: 2024 | C66: Identification of Optimal Machine Learning Algorithms and Molecular Fingerprints for Explainable Toxicity Prediction Models Using ToxCast/Tox21 Bioassay Data | D66: Molecular toxicity ML | E66: No | F66: Core | G66: High | H66: Transferable classical molecular toxicity / ecotoxicity ML | I66: ML / QSAR | J66: Chemical / molecular toxicity | K66: Regression | L66: Tox21 | M66: Morgan fingerprints; MACCS; Molecular fingerprints | N66: Random Forest; Logistic Regression | O66: NR in supplied metadata | P66: Results showed that 35 models revealed acceptable performance (F1 score or accuracy is 0.8 or higher). | Q66: No | R66: Transferable methodology for strengthening classical baselines, representation analysis, validation, interpretability or generalization beyond the base bee-toxicity study. | S66: ACS Omega | T66: https://doi.org/10.1021/acsomega.4c04474 | U66: https://www.scopus.com/pages/publications/85202159053?origin=resultslist | V66: All Open Access; Gold Open Access; Green Open Access
A67: 117 | B67: 2020 | C67: Classification of biodegradable substances using balanced random trees and boosted c5.0 decision trees | D67: Molecular toxicity ML | E67: No | F67: Core | G67: Medium | H67: Transferable classical molecular toxicity / ecotoxicity ML | I67: ML / QSAR | J67: Biodegradability | K67: Classification | L67: NR in supplied metadata | M67: Molecular descriptors | N67: SVM/SVR; kNN | O67: Bootstrap | P67: Based on the statistical measures, the experimental results showed that the proposed models outperform the classification results of the support vector machine (SVM), K-nearest neighbors (KNN), and discrimination analysis (DA). | Q67: No | R67: Transferable methodology for strengthening classical baselines, representation analysis, validation, interpretability or generalization beyond the base bee-toxicity study. | S67: International Journal of Environmental Research and Public Health | T67: https://doi.org/10.3390/ijerph17249322 | U67: https://www.scopus.com/pages/publications/85097652367?origin=resultslist | V67: All Open Access; Gold Open Access; Green Open Access
A68: 120 | B68: 2014 | C68: Merging applicability domains for in silico assessment of chemical mutagenicity | D68: Molecular toxicity ML | E68: No | F68: Core | G68: High | H68: Transferable classical molecular toxicity / ecotoxicity ML | I68: ML / QSAR | J68: Mutagenicity / Ames | K68: Predictive modeling / methodology | L68: NR in supplied metadata | M68: Molecular fingerprints; Molecular descriptors | N68: Random Forest | O68: Applicability-domain analysis | P68: NR in supplied abstract | Q68: No | R68: Transferable methodology for strengthening classical baselines, representation analysis, validation, interpretability or generalization beyond the base bee-toxicity study. | S68: Journal of Chemical Information and Modeling | T68: https://doi.org/10.1021/ci500016v | U68: https://www.scopus.com/pages/publications/84897002889?origin=resultslist
A69: 121 | B69: 2025 | C69: Deep learning for toxicity prediction | D69: Molecular toxicity ML | E69: No | F69: Core | G69: Medium | H69: Transferable classical molecular toxicity / ecotoxicity ML | I69: DL / neural network | J69: Hepatotoxicity / liver toxicity | K69: Regression | L69: NR in supplied metadata | M69: Molecular graphs; Molecular graphs / GNN representation; SMILES; 3D molecular information | N69: GNN; Transformer; Neural network; Ensemble | O69: NR in supplied metadata | P69: These developments underscore the importance of DL in enhancing toxicity prediction, with insights for addressing existing challenges and advancing predictive accuracy. | Q69: No | R69: Transferable methodology for strengthening classical baselines, representation analysis, validation, interpretability or generalization beyond the base bee-toxicity study. | S69: Deep Learning in Drug Design: Methods and Applications | T69: https://doi.org/10.1016/B978-0-44-332908-1.00028-3 | U69: https://www.scopus.com/pages/publications/105025830736?origin=resultslist
A70: 122 | B70: 2024 | C70: Comparative Study of Random Forest, Gradient Boosted Trees, Feedforward Neural Networks and Convolutional Neural Networks Using Fingerprints and Molecular Descriptors for Adverse Drug Reaction Prediction | D70: Molecular toxicity ML | E70: No | F70: Core | G70: Medium | H70: Transferable classical molecular toxicity / ecotoxicity ML | I70: DL / neural network | J70: Other / broad predictive task | K70: Predictive modeling / methodology | L70: NR in supplied metadata | M70: Morgan fingerprints; Molecular fingerprints; Molecular descriptors | N70: Random Forest; Gradient Boosting; CNN; Neural network | O70: NR in supplied metadata | P70: According to the experimental evaluation results RF and GBT had better results, with significant differences of even 20% in accuracy in certain cases, such as using molecular descriptors for Hepatobiliary disorders, than FNN and CNN. | Q70: No | R70: Transferable methodology for strengthening classical baselines, representation analysis, validation, interpretability or generalization beyond the base bee-toxicity study. | S70: Procedia Computer Science | T70: https://doi.org/10.1016/j.procs.2024.09.702 | U70: https://www.scopus.com/pages/publications/85213325416?origin=resultslist | V70: All Open Access; Gold Open Access
A71: 123 | B71: 2021 | C71: Shedding light on “Black Box” machine learning models for predicting the reactivity of HO[rad] radicals toward organic compounds | D71: Molecular toxicity ML | E71: No | F71: Core | G71: Medium | H71: Transferable classical molecular toxicity / ecotoxicity ML | I71: DL / neural network | J71: Other / broad predictive task | K71: Regression | L71: NR in supplied metadata | M71: Molecular fingerprints; Molecular descriptors; Molecular graphs | N71: XGBoost; Gradient Boosting; Neural network; Ensemble | O71: NR in supplied metadata | P71: We then developed an ensemble model combining the DNN with XGBoost, which achieved satisfactory predictive performance for all three datasets: Training dataset: R-square (R2) 0.89–0.91, root-mean-squared-error (RMSE) 0.21–0.23, and mean absolute error (MAE) 0.15–0.17; Validation dataset: R2 0.63–0.78, RMSE 0.29–0.32, and MAE 0.21–0.25; and Test dat | Q71: No | R71: Transferable methodology for strengthening classical baselines, representation analysis, validation, interpretability or generalization beyond the base bee-toxicity study. | S71: Chemical Engineering Journal | T71: https://doi.org/10.1016/j.cej.2020.126627 | U71: https://www.scopus.com/pages/publications/85089414417?origin=resultslist | V71: All Open Access; Green Open Access
A72: 124 | B72: 2026 | C72: Characterizing chemical toxicity for life cycle assessment using machine learning and deep learning models based on environmental footprint-methodological comparison & textile case study | D72: Molecular toxicity ML | E72: No | F72: Core | G72: High | H72: Transferable classical molecular toxicity / ecotoxicity ML | I72: DL / neural network | J72: Chemical ecotoxicity | K72: Regression | L72: NR in supplied metadata | M72: Molecular descriptors; Molecular graphs; Molecular graphs / GNN representation; SMILES | N72: Random Forest; XGBoost; GNN; Neural network | O72: Applicability-domain analysis | P72: Predictive performance is strongly target-dependent, with ecotoxicity CFs showing consistently higher predictability (R2 = 0.47–0.67) than human toxicity CFs (R2 = 0.44–0.56). | Q72: No | R72: Transferable methodology for strengthening classical baselines, representation analysis, validation, interpretability or generalization beyond the base bee-toxicity study. | S72: RSC Sustainability | T72: https://doi.org/10.1039/d6su00023a | U72: https://www.scopus.com/pages/publications/105044060625?origin=resultslist | V72: All Open Access; Gold Open Access
A73: 125 | B73: 2019 | C73: Using Molecular Fingerprints as Descriptors in Toxicity Prediction: A Survey | D73: Molecular toxicity ML | E73: No | F73: Core | G73: Medium | H73: Transferable classical molecular toxicity / ecotoxicity ML | I73: ML / QSAR | J73: Chemical / molecular toxicity | K73: Review / guidance | L73: Tox21 | M73: Molecular fingerprints; Molecular descriptors; Molecular graphs | N73: ML / QSAR model | O73: NR in supplied metadata | P73: NR in supplied abstract | Q73: No | R73: Transferable methodology for strengthening classical baselines, representation analysis, validation, interpretability or generalization beyond the base bee-toxicity study. | S73: Proceedings - 2019 IEEE International Conference on Bioinformatics and Biomedicine, BIBM 2019 | T73: https://doi.org/10.1109/BIBM47256.2019.8982990 | U73: https://www.scopus.com/pages/publications/85084336399?origin=resultslist
A74: 126 | B74: 2022 | C74: A Comparative Study of the Performance for Predicting Biodegradability Classification: The Quantitative Structure–Activity Relationship Model vs the Graph Convolutional Network | D74: Molecular toxicity ML | E74: No | F74: Core | G74: Medium | H74: Transferable classical molecular toxicity / ecotoxicity ML | I74: DL / neural network | J74: Biodegradability | K74: Classification | L74: NR in supplied metadata | M74: MACCS; Molecular fingerprints; Molecular descriptors; Molecular graphs | N74: GCN | O74: NR in supplied metadata | P74: The performance comparison of the methods confirms that the GCN model is more straightforward to implement and more stable; the specificity and sensitivity values are almost identical without specific descriptors or fingerprints. | Q74: No | R74: Transferable methodology for strengthening classical baselines, representation analysis, validation, interpretability or generalization beyond the base bee-toxicity study. | S74: ACS Omega | T74: https://doi.org/10.1021/acsomega.1c06274 | U74: https://www.scopus.com/pages/publications/85123916912?origin=resultslist | V74: All Open Access; Gold Open Access; Green Open Access
A75: 129 | B75: 2025 | C75: Ecotoxicity prediction of chemical compounds using machine learning and different molecular structure representations | D75: Molecular toxicity ML | E75: No | F75: Core | G75: Medium | H75: Transferable classical molecular toxicity / ecotoxicity ML | I75: ML / QSAR | J75: Chemical ecotoxicity | K75: Classification / regression | L75: NR in supplied metadata | M75: ECFP; MACCS; Molecular fingerprints; Molecular descriptors | N75: ML / QSAR model | O75: Cross-validation | P75: The best model achieved an average RMSE of 0.740, an R² of 0.708, and an MAE of 0.546 through ten-fold cross-validation. | Q75: No | R75: Transferable methodology for strengthening classical baselines, representation analysis, validation, interpretability or generalization beyond the base bee-toxicity study. | S75: Green Analytical Chemistry | T75: https://doi.org/10.1016/j.greeac.2025.100273 | U75: https://www.scopus.com/pages/publications/105004306666?origin=resultslist | V75: All Open Access; Gold Open Access; Green Open Access
A76: 130 | B76: 2026 | C76: Neurotoxicity Prediction of Compounds: Integrating Knowledge-Guided Graph Representations with Machine Learning Approaches | D76: Molecular toxicity ML | E76: No | F76: Core | G76: High | H76: Transferable classical molecular toxicity / ecotoxicity ML | I76: DL / neural network | J76: ADME-Tox / ADMET properties | K76: Classification | L76: NR in supplied metadata | M76: Molecular fingerprints | N76: Transformer | O76: NR in supplied metadata | P76: The KPGT-MLP model achieved the best balanced performance, with an accuracy (ACC) of 0.8928 and an ROC-AUC of 0.9459, clearly outperforming traditional fingerprint-based models, MolFormer-based models, and general prediction tools such as DI-NeuroT and ADMETlab 3.0. | Q76: No | R76: Transferable methodology for strengthening classical baselines, representation analysis, validation, interpretability or generalization beyond the base bee-toxicity study. | S76: International Journal of Molecular Sciences | T76: https://doi.org/10.3390/ijms27083543 | U76: https://www.scopus.com/pages/publications/105037018549?origin=resultslist | V76: All Open Access; Gold Open Access; Green Open Access
A77: 131 | B77: 2023 | C77: Implementation of the Grey Wolf Algorithm in Optimization of Artificial Neural Network Method for Fingerprint-Based Toxicity Prediction | D77: Molecular toxicity ML | E77: No | F77: Core | G77: Medium | H77: Transferable classical molecular toxicity / ecotoxicity ML | I77: DL / neural network | J77: Chemical / molecular toxicity | K77: Predictive modeling / methodology | L77: Tox21 | M77: Molecular fingerprints | N77: Neural network | O77: NR in supplied metadata | P77: According to the result, we obtained the best model from ANN with 2 hidden layers, tanh activation function, and adam optimizer, getting F1-score results and accuracy on test data with values of 0.590 and 0.887 respectively. | Q77: No | R77: Transferable methodology for strengthening classical baselines, representation analysis, validation, interpretability or generalization beyond the base bee-toxicity study. | S77: Proceedings - 2023 6th International Conference on Computer and Informatics Engineering: AI Trust, Risk and Security Management (AI Trism), IC2IE 2023 | T77: https://doi.org/10.1109/IC2IE60547.2023.10331599 | U77: https://www.scopus.com/pages/publications/85180748562?origin=resultslist
A78: 132 | B78: 2019 | C78: ToxicBlend: Virtual screening of toxic compounds with ensemble predictors | D78: Molecular toxicity ML | E78: No | F78: Core | G78: Medium | H78: Transferable classical molecular toxicity / ecotoxicity ML | I78: ML / QSAR | J78: Chemical / molecular toxicity | K78: Predictive modeling / methodology | L78: Tox21 | M78: Molecular fingerprints; Molecular descriptors; Molecular graphs; SMILES | N78: Gradient Boosting; CNN; Neural network; Ensemble | O78: NR in supplied metadata | P78: NR in supplied abstract | Q78: No | R78: Transferable methodology for strengthening classical baselines, representation analysis, validation, interpretability or generalization beyond the base bee-toxicity study. | S78: Computational Toxicology | T78: https://doi.org/10.1016/j.comtox.2019.01.001 | U78: https://www.scopus.com/pages/publications/85060348439?origin=resultslist | V78: All Open Access; Green Open Access
A79: 133 | B79: 2025 | C79: Descriptor-Based Explainable QSAR Modeling Approaches for the Prediction of Respiratory Toxicity of Volatile and Gas-Phase Chemicals | D79: Molecular toxicity ML | E79: No | F79: Core | G79: High | H79: Transferable classical molecular toxicity / ecotoxicity ML | I79: ML / QSAR | J79: Chemical ecotoxicity | K79: Review / guidance | L79: NR in supplied metadata | M79: Molecular descriptors | N79: Random Forest; XGBoost; Logistic Regression; Bayesian model | O79: NR in supplied metadata | P79: Employing molecular descriptor selection, correlation analyses, and outlier detection, random forest and XGBoost emerged as the most accurate models, each achieving a high accuracy of 0.915, with ROC areas of 0.992 and 0.986, respectively. | Q79: No | R79: Transferable methodology for strengthening classical baselines, representation analysis, validation, interpretability or generalization beyond the base bee-toxicity study. | S79: Journal of Applied Toxicology | T79: https://doi.org/10.1002/jat.4859 | U79: https://www.scopus.com/pages/publications/105010748366?origin=resultslist
A80: 134 | B80: 2016 | C80: Identifying biological pathway interrupting toxins using multi-tree ensembles | D80: Molecular toxicity ML | E80: No | F80: Core | G80: High | H80: Transferable classical molecular toxicity / ecotoxicity ML | I80: DL / neural network | J80: Chemical / molecular toxicity | K80: Classification | L80: Tox21 | M80: Molecular fingerprints | N80: Random Forest; Ensemble | O80: NR in supplied metadata | P80: The results clearly demonstrate that the generic approach presented in this paper is comparable to advanced deep learning and domain-specific solutions. | Q80: No | R80: Transferable methodology for strengthening classical baselines, representation analysis, validation, interpretability or generalization beyond the base bee-toxicity study. | S80: Frontiers in Environmental Science | T80: https://doi.org/10.3389/fenvs.2016.00052 | U80: https://www.scopus.com/pages/publications/85017178111?origin=resultslist | V80: All Open Access; Gold Open Access; Green Open Access
A81: 135 | B81: 2025 | C81: Machine learning prediction model for emerging pollutants-induced activities of 12 nuclear receptors; [新污染物诱导 12 种细胞核受体相关活性的机器学习预测模型] | D81: Molecular toxicity ML | E81: No | F81: Core | G81: Medium | H81: Transferable classical molecular toxicity / ecotoxicity ML | I81: ML / QSAR | J81: Chemical / molecular toxicity | K81: Review / guidance | L81: Tox21 | M81: Molecular descriptors; SMILES | N81: XGBoost | O81: NR in supplied metadata | P81: Model performance was evaluated by calculating the accuracy of the test set, and data availability was characterized in terms of the application domain. | Q81: No | R81: Transferable methodology for strengthening classical baselines, representation analysis, validation, interpretability or generalization beyond the base bee-toxicity study. | S81: Chinese Journal of Chromatography (Se Pu) | T81: https://doi.org/10.3724/SP.J.1123.2024.12008 | U81: https://www.scopus.com/pages/publications/105014292493?origin=resultslist | V81: All Open Access; Bronze Open Access; Green Open Access
A82: 136 | B82: 2026 | C82: Metabolomics driven, data augmented machine learning for predicting toxicity of microplastic mixtures | D82: Molecular toxicity ML | E82: No | F82: Core | G82: Medium | H82: Transferable classical molecular toxicity / ecotoxicity ML | I82: ML / QSAR | J82: Cytotoxicity | K82: Regression | L82: NR in supplied metadata | M82: Molecular descriptors; Mass spectra | N82: Random Forest; Gradient Boosting; SVM/SVR | O82: NR in supplied metadata | P82: NR in supplied abstract | Q82: No | R82: Transferable methodology for strengthening classical baselines, representation analysis, validation, interpretability or generalization beyond the base bee-toxicity study. | S82: Ecotoxicology and Environmental Safety | T82: https://doi.org/10.1016/j.ecoenv.2026.119944 | U82: https://www.scopus.com/pages/publications/105032246292?origin=resultslist | V82: All Open Access; Gold Open Access
A83: 137 | B83: 2023 | C83: Predicting the ecotoxicity of endocrine disruptive chemicals: Multitasking in silico approaches towards global models | D83: Molecular toxicity ML | E83: No | F83: Core | G83: High | H83: Transferable classical molecular toxicity / ecotoxicity ML | I83: ML / QSAR | J83: Cytotoxicity | K83: Predictive modeling / methodology | L83: NR in supplied metadata | M83: NR in supplied metadata | N83: ML / QSAR model | O83: NR in supplied metadata | P83: NR in supplied abstract | Q83: No | R83: Transferable methodology for strengthening classical baselines, representation analysis, validation, interpretability or generalization beyond the base bee-toxicity study. | S83: Science of the Total Environment | T83: https://doi.org/10.1016/j.scitotenv.2023.164337 | U83: https://www.scopus.com/pages/publications/85160448388?origin=resultslist | V83: All Open Access; Hybrid Gold Open Access
A84: 138 | B84: 2026 | C84: Predicting the toxicity of organic chemicals to Tetrahymena pyriformis based on machine learning and interpretable models | D84: Molecular toxicity ML | E84: No | F84: Core | G84: Medium | H84: Transferable classical molecular toxicity / ecotoxicity ML | I84: ML / QSAR | J84: Chemical / molecular toxicity | K84: Regression | L84: 1792 compounds | M84: Molecular descriptors | N84: Random Forest; XGBoost; SVM/SVR; kNN; Ensemble | O84: NR in supplied metadata | P84: The XGBoost model outperformed others, achieving a coefficient of determination (R²) of 0.918 (training set) and 0.866 (test set), indicating strong robustness and predictive capability. | Q84: No | R84: Transferable methodology for strengthening classical baselines, representation analysis, validation, interpretability or generalization beyond the base bee-toxicity study. | S84: Process Safety and Environmental Protection | T84: https://doi.org/10.1016/j.psep.2025.108314 | U84: https://www.scopus.com/pages/publications/105024900042?origin=resultslist
A85: 139 | B85: 2026 | C85: Machine Learning-Based Toxicity Prediction Using Molecular Fingerprints | D85: Molecular toxicity ML | E85: No | F85: Core | G85: Medium | H85: Transferable classical molecular toxicity / ecotoxicity ML | I85: ML / QSAR | J85: Chemical / molecular toxicity | K85: Predictive modeling / methodology | L85: Tox21 | M85: Morgan fingerprints; Molecular fingerprints; Molecular descriptors | N85: XGBoost; Gradient Boosting; SVM/SVR | O85: Cross-validation | P85: Model performance is assessed using ROC-AUC, Precision-Recall AUC, balanced accuracy, and Matthews correlation coefficient. | Q85: No | R85: Transferable methodology for strengthening classical baselines, representation analysis, validation, interpretability or generalization beyond the base bee-toxicity study. | S85: Proceedings of the 6th International Conference on Trends in Material Science and Inventive Materials, ICTMIM 2026 | T85: https://doi.org/10.1109/ICTMIM68190.2026.11506858 | U85: https://www.scopus.com/pages/publications/105041461939?origin=resultslist
A86: 140 | B86: 2020 | C86: Improvement in ADMET Prediction with Multitask Deep Featurization | D86: Molecular toxicity ML | E86: No | F86: Core | G86: Medium | H86: Transferable classical molecular toxicity / ecotoxicity ML | I86: DL / neural network | J86: ADME-Tox / ADMET properties | K86: Predictive modeling / methodology | L86: NR in supplied metadata | M86: Molecular fingerprints | N86: Random Forest; CNN; Neural network | O86: Cross-validation | P86: By applying graph convolutions to this explicit molecular representation, we achieve, to our knowledge, unprecedented accuracy in prediction of ADMET properties. | Q86: No | R86: Transferable methodology for strengthening classical baselines, representation analysis, validation, interpretability or generalization beyond the base bee-toxicity study. | S86: Journal of Medicinal Chemistry | T86: https://doi.org/10.1021/acs.jmedchem.9b02187 | U86: https://www.scopus.com/pages/publications/85090078751?origin=resultslist
A87: 141 | B87: 2026 | C87: Screening toxic transformation products of emerging pollutants in advanced oxidation processes with 3D deep learning and in vitro assays | D87: Molecular toxicity ML | E87: No | F87: Core | G87: Medium | H87: Transferable classical molecular toxicity / ecotoxicity ML | I87: Classical ML with quantum-chemical information | J87: Mutagenicity / Ames | K87: Predictive modeling / methodology | L87: NR in supplied metadata | M87: Molecular descriptors; Molecular graphs; Molecular graphs / GNN representation; 3D molecular information | N87: GNN; GAT; Transformer; Neural network | O87: Cross-validation | P87: NR in supplied abstract | Q87: Quantum chemistry / QM features; not QML | R87: Transferable methodology for strengthening classical baselines, representation analysis, validation, interpretability or generalization beyond the base bee-toxicity study. | S87: Water Research | T87: https://doi.org/10.1016/j.watres.2026.125499 | U87: https://www.scopus.com/pages/publications/105029771732?origin=resultslist
A88: 142 | B88: 2025 | C88: CLSSATP: Contrastive learning and self-supervised learning model for aquatic toxicity prediction | D88: Molecular toxicity ML | E88: No | F88: Core | G88: High | H88: Transferable classical molecular toxicity / ecotoxicity ML | I88: DL / neural network | J88: Chemical ecotoxicity | K88: Review / guidance | L88: NR in supplied metadata | M88: Molecular fingerprints; Molecular graphs; Molecular graphs / GNN representation | N88: SVM/SVR; GNN; Neural network | O88: NR in supplied metadata | P88: In this regard, deep learning methods offer significant advantages over traditional experimental approaches in terms of cost, accuracy, and generalization ability. | Q88: No | R88: Transferable methodology for strengthening classical baselines, representation analysis, validation, interpretability or generalization beyond the base bee-toxicity study. | S88: Aquatic Toxicology | T88: https://doi.org/10.1016/j.aquatox.2025.107244 | U88: https://www.scopus.com/pages/publications/85214475384?origin=resultslist
A89: 143 | B89: 2021 | C89: FP-ADMET: a compendium of fingerprint-based ADMET prediction models | D89: Molecular toxicity ML | E89: No | F89: Core | G89: Medium | H89: Transferable classical molecular toxicity / ecotoxicity ML | I89: ML / QSAR | J89: ADME-Tox / ADMET properties | K89: Classification | L89: NR in supplied metadata | M89: Molecular fingerprints; Molecular descriptors; 3D molecular information | N89: Random Forest | O89: NR in supplied metadata | P89: We find that for a majority of the properties, fingerprint-based random forest models yield comparable or better performance compared with traditional 2D/3D molecular descriptors. | Q89: No | R89: Transferable methodology for strengthening classical baselines, representation analysis, validation, interpretability or generalization beyond the base bee-toxicity study. | S89: Journal of Cheminformatics | T89: https://doi.org/10.1186/s13321-021-00557-5 | U89: https://www.scopus.com/pages/publications/85115864342?origin=resultslist | V89: All Open Access; Gold Open Access; Green Open Access
A90: 144 | B90: 2025 | C90: PE-GCL: Advancing pesticide ecotoxicity prediction with graph contrastive learning | D90: Molecular toxicity ML | E90: No | F90: Core | G90: High | H90: Transferable classical molecular toxicity / ecotoxicity ML | I90: DL / neural network | J90: Chemical ecotoxicity | K90: Predictive modeling / methodology | L90: NR in supplied metadata | M90: Molecular graphs / GNN representation | N90: GNN; Neural network | O90: External validation | P90: Performance evaluation showed that the PE-GCL outperformed traditional supervised models across most prediction tasks, whereas independent external validation confirmed its superior predictive accuracy for unseen data. | Q90: No | R90: Transferable methodology for strengthening classical baselines, representation analysis, validation, interpretability or generalization beyond the base bee-toxicity study. | S90: Journal of Hazardous Materials | T90: https://doi.org/10.1016/j.jhazmat.2025.137261 | U90: https://www.scopus.com/pages/publications/85215253354?origin=resultslist
A91: 145 | B91: 2026 | C91: An interpretable and resource-efficient machine learning framework for classifying PBT chemicals | D91: Molecular toxicity ML | E91: No | F91: Core | G91: High | H91: Transferable classical molecular toxicity / ecotoxicity ML | I91: ML / QSAR | J91: Chemical / molecular toxicity | K91: Review / guidance | L91: NR in supplied metadata | M91: MACCS; Molecular fingerprints; Molecular descriptors; Molecular graphs | N91: CatBoost | O91: Applicability-domain analysis | P91: CatBoost achieved the best performance with generalization F1-score of 0.9153 and was selected for subsequent reliability and interpretability analyses. | Q91: No | R91: Transferable methodology for strengthening classical baselines, representation analysis, validation, interpretability or generalization beyond the base bee-toxicity study. | S91: Journal of Hazardous Materials Advances | T91: https://doi.org/10.1016/j.hazadv.2026.101162 | U91: https://www.scopus.com/pages/publications/105036251257?origin=resultslist | V91: All Open Access; Gold Open Access
A92: 146 | B92: 2020 | C92: A toxicity prediction tool for potential agonist/antagonist activities in molecular initiating events based on chemical structures | D92: Molecular toxicity ML | E92: No | F92: Core | G92: High | H92: Transferable classical molecular toxicity / ecotoxicity ML | I92: ML / QSAR | J92: Chemical / molecular toxicity | K92: Predictive modeling / methodology | L92: Tox21 | M92: Molecular descriptors; 3D molecular information | N92: XGBoost | O92: Applicability-domain analysis | P92: NR in supplied abstract | Q92: No | R92: Transferable methodology for strengthening classical baselines, representation analysis, validation, interpretability or generalization beyond the base bee-toxicity study. | S92: International Journal of Molecular Sciences | T92: https://doi.org/10.3390/ijms21217853 | U92: https://www.scopus.com/pages/publications/85094158469?origin=resultslist | V92: All Open Access; Gold Open Access; Green Open Access
A93: 147 | B93: 2025 | C93: Revolutionizing toxicity predictions of diverse chemicals to protect human health: Comparative QSAR and q-RASAR modeling | D93: Molecular toxicity ML | E93: No | F93: Core | G93: High | H93: Transferable classical molecular toxicity / ecotoxicity ML | I93: ML / QSAR | J93: Neurotoxicity | K93: Regression | L93: DrugBank | M93: NR in supplied metadata | N93: Read-across; RASAR | O93: External validation | P93: We developed the first-ever predictive toxicity models combining QSAR and similarity-based read-across techniques to enhance accuracy, utilizing the TOXRIC database. | Q93: No | R93: Transferable methodology for strengthening classical baselines, representation analysis, validation, interpretability or generalization beyond the base bee-toxicity study. | S93: Toxicology Letters | T93: https://doi.org/10.1016/j.toxlet.2025.06.019 | U93: https://www.scopus.com/pages/publications/105009755568?origin=resultslist
A94: 148 | B94: 2025 | C94: Part II. Systematic development of machine learning models for predicting human and ecotoxicity from in vivo OECD test guideline data | D94: Molecular toxicity ML | E94: No | F94: Core | G94: Medium | H94: Transferable classical molecular toxicity / ecotoxicity ML | I94: ML / QSAR | J94: Mutagenicity / Ames | K94: Regression | L94: NR in supplied metadata | M94: Morgan fingerprints; MACCS; Molecular fingerprints; Molecular descriptors | N94: Random Forest; XGBoost; Gradient Boosting; Logistic Regression | O94: NR in supplied metadata | P94: Model performance was evaluated using standard metrics, including F1 score, precision, recall, accuracy, AUC-ROC. | Q94: No | R94: Transferable methodology for strengthening classical baselines, representation analysis, validation, interpretability or generalization beyond the base bee-toxicity study. | S94: Computational Toxicology | T94: https://doi.org/10.1016/j.comtox.2025.100369 | U94: https://www.scopus.com/pages/publications/105011772006?origin=resultslist | V94: All Open Access; Hybrid Gold Open Access
A95: 149 | B95: 2023 | C95: QSAR modeling of chronic rat toxicity of diverse organic chemicals | D95: Molecular toxicity ML | E95: No | F95: Core | G95: Medium | H95: Transferable classical molecular toxicity / ecotoxicity ML | I95: ML / QSAR | J95: Chemical / molecular toxicity | K95: Regression | L95: DrugBank | M95: Molecular descriptors; Molecular graphs | N95: ML / QSAR model | O95: NR in supplied metadata | P95: We validated the developed partial least squares (PLS) model statistically, and the results demonstrate the model's reliability, robustness, and predictive ability (R2 = 0.60, Q2 (LOO) = 0.58, Q2 F1 = 0.56, and Q2 F2 = 0.56). | Q95: No | R95: Transferable methodology for strengthening classical baselines, representation analysis, validation, interpretability or generalization beyond the base bee-toxicity study. | S95: Computational Toxicology | T95: https://doi.org/10.1016/j.comtox.2023.100270 | U95: https://www.scopus.com/pages/publications/85151732750?origin=resultslist
A96: 150 | B96: 2025 | C96: Hybrid intelligence for environmental pollution: biodegradability assessment of organic compounds through multimodal integration of graph attention networks and QSAR models | D96: Molecular toxicity ML | E96: No | F96: Core | G96: High | H96: Transferable classical molecular toxicity / ecotoxicity ML | I96: ML / QSAR | J96: Biodegradability | K96: Classification | L96: NR in supplied metadata | M96: Molecular descriptors | N96: Random Forest; Gradient Boosting; GAT; Ensemble | O96: NR in supplied metadata | P96: The GAT models demonstrated a stable function and generally higher specificity on the validation set compared to a graph convolutional network, although definitive superiority is challenging to establish owing to overlapping standard deviations. | Q96: No | R96: Transferable methodology for strengthening classical baselines, representation analysis, validation, interpretability or generalization beyond the base bee-toxicity study. | S96: Environmental Science: Processes and Impacts | T96: https://doi.org/10.1039/d4em00594e | U96: https://www.scopus.com/pages/publications/105000155850?origin=resultslist
A97: 151 | B97: 2024 | C97: Multi-Endpoint Acute Toxicity Assessment of Organic Compounds Using Large-Scale Machine Learning Modeling | D97: Molecular toxicity ML | E97: No | F97: Core | G97: Medium | H97: Transferable classical molecular toxicity / ecotoxicity ML | I97: DL / neural network | J97: Acute chemical toxicity | K97: Regression | L97: 80,000 compounds | M97: Molecular descriptors | N97: CNN; Neural network | O97: NR in supplied metadata | P97: NR in supplied abstract | Q97: No | R97: Transferable methodology for strengthening classical baselines, representation analysis, validation, interpretability or generalization beyond the base bee-toxicity study. | S97: Environmental Science and Technology | T97: https://doi.org/10.1021/acs.est.4c01017 | U97: https://www.scopus.com/pages/publications/85194318094?origin=resultslist
A98: 152 | B98: 2023 | C98: Accurate clinical toxicity prediction using multi-task deep neural nets and contrastive molecular explanations | D98: Molecular toxicity ML | E98: No | F98: Core | G98: High | H98: Transferable classical molecular toxicity / ecotoxicity ML | I98: DL / neural network | J98: Mutagenicity / Ames | K98: Predictive modeling / methodology | L98: MoleculeNet | M98: Morgan fingerprints; Molecular fingerprints; SMILES | N98: ML / QSAR model | O98: NR in supplied metadata | P98: A multi-task deep learning model accurately predicts toxicity for all endpoints, including clinical, as indicated by the area under the Receiver Operator Characteristic curve and balanced accuracy. | Q98: No | R98: Transferable methodology for strengthening classical baselines, representation analysis, validation, interpretability or generalization beyond the base bee-toxicity study. | S98: Scientific Reports | T98: https://doi.org/10.1038/s41598-023-31169-8 | U98: https://www.scopus.com/pages/publications/85150957576?origin=resultslist | V98: All Open Access; Gold Open Access; Green Open Access
A99: 153 | B99: 2022 | C99: Identifying Protein Features and Pathways Responsible for Toxicity Using Machine Learning and Tox21: Implications for Predictive Toxicology | D99: Molecular toxicity ML | E99: No | F99: Core | G99: High | H99: Transferable classical molecular toxicity / ecotoxicity ML | I99: ML / QSAR | J99: Chemical / molecular toxicity | K99: Predictive modeling / methodology | L99: 10,000 compounds | M99: Molecular descriptors | N99: Random Forest | O99: NR in supplied metadata | P99: NR in supplied abstract | Q99: No | R99: Transferable methodology for strengthening classical baselines, representation analysis, validation, interpretability or generalization beyond the base bee-toxicity study. | S99: Molecules | T99: https://doi.org/10.3390/molecules27093021 | U99: https://www.scopus.com/pages/publications/85130022073?origin=resultslist | V99: All Open Access; Gold Open Access; Green Open Access
